{
"meta":{"test_sets":[],"test_metrics":[],"learn_metrics":[{"best_value":"Min","name":"RMSE"}],"launch_mode":"Train","parameters":"","iteration_count":1000,"learn_sets":["learn"],"name":"experiment"},
"iterations":[
{"learn":[3.829865305],"iteration":0,"passed_time":0.1247294862,"remaining_time":124.6047567},
{"learn":[3.735399068],"iteration":1,"passed_time":0.1354663007,"remaining_time":67.59768405},
{"learn":[3.65278985],"iteration":2,"passed_time":0.1461261144,"remaining_time":48.56257868},
{"learn":[3.571414367],"iteration":3,"passed_time":0.1560143967,"remaining_time":38.84758477},
{"learn":[3.500235879],"iteration":4,"passed_time":0.1663683253,"remaining_time":33.10729674},
{"learn":[3.433425707],"iteration":5,"passed_time":0.1768405089,"remaining_time":29.29657764},
{"learn":[3.371361458],"iteration":6,"passed_time":0.1865634514,"remaining_time":26.46535818},
{"learn":[3.310917691],"iteration":7,"passed_time":0.1983374249,"remaining_time":24.59384069},
{"learn":[3.258721347],"iteration":8,"passed_time":0.2095131694,"remaining_time":23.06972787},
{"learn":[3.208854019],"iteration":9,"passed_time":0.2203499297,"remaining_time":21.81464304},
{"learn":[3.157800677],"iteration":10,"passed_time":0.23012591,"remaining_time":20.69041136},
{"learn":[3.111205848],"iteration":11,"passed_time":0.2397871318,"remaining_time":19.74247385},
{"learn":[3.071602162],"iteration":12,"passed_time":0.2496952622,"remaining_time":18.9576326},
{"learn":[3.031525807],"iteration":13,"passed_time":0.2587944483,"remaining_time":18.22652329},
{"learn":[2.993548838],"iteration":14,"passed_time":0.2705380242,"remaining_time":17.76533025},
{"learn":[2.956848234],"iteration":15,"passed_time":0.2803833475,"remaining_time":17.24357587},
{"learn":[2.925590373],"iteration":16,"passed_time":0.2888968285,"remaining_time":16.70503426},
{"learn":[2.894295352],"iteration":17,"passed_time":0.3026292928,"remaining_time":16.5101092},
{"learn":[2.866708193],"iteration":18,"passed_time":0.3123689314,"remaining_time":16.12810114},
{"learn":[2.838254882],"iteration":19,"passed_time":0.3227861564,"remaining_time":15.81652166},
{"learn":[2.810728249],"iteration":20,"passed_time":0.3298601384,"remaining_time":15.3777655},
{"learn":[2.785950476],"iteration":21,"passed_time":0.3351432671,"remaining_time":14.8986416},
{"learn":[2.763938242],"iteration":22,"passed_time":0.3402513531,"remaining_time":14.45328574},
{"learn":[2.740060458],"iteration":23,"passed_time":0.3440820766,"remaining_time":13.99267112},
{"learn":[2.720945829],"iteration":24,"passed_time":0.3477213886,"remaining_time":13.56113416},
{"learn":[2.700481178],"iteration":25,"passed_time":0.3510009369,"remaining_time":13.1490351},
{"learn":[2.682261822],"iteration":26,"passed_time":0.3543073336,"remaining_time":12.7681865},
{"learn":[2.663779246],"iteration":27,"passed_time":0.3575370591,"remaining_time":12.41164362},
{"learn":[2.64690039],"iteration":28,"passed_time":0.3600499779,"remaining_time":12.0554665},
{"learn":[2.629743291],"iteration":29,"passed_time":0.3633457301,"remaining_time":11.74817861},
{"learn":[2.614234407],"iteration":30,"passed_time":0.3664752695,"remaining_time":11.45530762},
{"learn":[2.596099601],"iteration":31,"passed_time":0.3693879597,"remaining_time":11.17398578},
{"learn":[2.581809241],"iteration":32,"passed_time":0.3729674815,"remaining_time":10.92907741},
{"learn":[2.568716486],"iteration":33,"passed_time":0.3755910096,"remaining_time":10.67120339},
{"learn":[2.554341518],"iteration":34,"passed_time":0.3785005308,"remaining_time":10.43580035},
{"learn":[2.544185588],"iteration":35,"passed_time":0.3809289029,"remaining_time":10.20042951},
{"learn":[2.531757485],"iteration":36,"passed_time":0.383311463,"remaining_time":9.976457807},
{"learn":[2.519179111],"iteration":37,"passed_time":0.3871169874,"remaining_time":9.800172155},
{"learn":[2.507853334],"iteration":38,"passed_time":0.3899587621,"remaining_time":9.608983856},
{"learn":[2.496133517],"iteration":39,"passed_time":0.3928176525,"remaining_time":9.42762366},
{"learn":[2.484965244],"iteration":40,"passed_time":0.3955848181,"remaining_time":9.252825379},
{"learn":[2.472712526],"iteration":41,"passed_time":0.3980282104,"remaining_time":9.078833942},
{"learn":[2.460296878],"iteration":42,"passed_time":0.4022268607,"remaining_time":8.95188618},
{"learn":[2.450358932],"iteration":43,"passed_time":0.4049202324,"remaining_time":8.797812322},
{"learn":[2.440253741],"iteration":44,"passed_time":0.4076984106,"remaining_time":8.652266269},
{"learn":[2.430520627],"iteration":45,"passed_time":0.4106525311,"remaining_time":8.516576407},
{"learn":[2.419309174],"iteration":46,"passed_time":0.4131462452,"remaining_time":8.377199398},
{"learn":[2.410647123],"iteration":47,"passed_time":0.4170703078,"remaining_time":8.271894439},
{"learn":[2.401102226],"iteration":48,"passed_time":0.420132747,"remaining_time":8.154004946},
{"learn":[2.392416567],"iteration":49,"passed_time":0.4229532496,"remaining_time":8.036111743},
{"learn":[2.384992346],"iteration":50,"passed_time":0.4257987333,"remaining_time":7.923196037},
{"learn":[2.378056816],"iteration":51,"passed_time":0.4284170613,"remaining_time":7.810372578},
{"learn":[2.371217991],"iteration":52,"passed_time":0.4322755606,"remaining_time":7.723867092},
{"learn":[2.364300942],"iteration":53,"passed_time":0.4351753567,"remaining_time":7.623627545},
{"learn":[2.356929891],"iteration":54,"passed_time":0.4379151126,"remaining_time":7.524177843},
{"learn":[2.35022966],"iteration":55,"passed_time":0.4407795934,"remaining_time":7.430284574},
{"learn":[2.344046359],"iteration":56,"passed_time":0.4435264855,"remaining_time":7.337639928},
{"learn":[2.33804303],"iteration":57,"passed_time":0.4479467265,"remaining_time":7.275272697},
{"learn":[2.329967029],"iteration":58,"passed_time":0.4508376361,"remaining_time":7.190478229},
{"learn":[2.323387467],"iteration":59,"passed_time":0.4535681159,"remaining_time":7.105900483},
{"learn":[2.316342229],"iteration":60,"passed_time":0.4564391665,"remaining_time":7.02617012},
{"learn":[2.308273115],"iteration":61,"passed_time":0.4589221979,"remaining_time":6.943048735},
{"learn":[2.300450192],"iteration":62,"passed_time":0.4640783323,"remaining_time":6.902244403},
{"learn":[2.293238291],"iteration":63,"passed_time":0.4672885295,"remaining_time":6.834094745},
{"learn":[2.286751675],"iteration":64,"passed_time":0.4703904203,"remaining_time":6.766385276},
{"learn":[2.279670082],"iteration":65,"passed_time":0.4736930657,"remaining_time":6.703474597},
{"learn":[2.274762916],"iteration":66,"passed_time":0.4784194288,"remaining_time":6.66216906},
{"learn":[2.2694399],"iteration":67,"passed_time":0.481545291,"remaining_time":6.600003106},
{"learn":[2.263012573],"iteration":68,"passed_time":0.4847794456,"remaining_time":6.541009622},
{"learn":[2.25756938],"iteration":69,"passed_time":0.4879609142,"remaining_time":6.482909289},
{"learn":[2.252036416],"iteration":70,"passed_time":0.492034146,"remaining_time":6.438024249},
{"learn":[2.247789011],"iteration":71,"passed_time":0.4955889934,"remaining_time":6.387591471},
{"learn":[2.242000312],"iteration":72,"passed_time":0.498524203,"remaining_time":6.330574468},
{"learn":[2.236664127],"iteration":73,"passed_time":0.5023379134,"remaining_time":6.286012268},
{"learn":[2.232281605],"iteration":74,"passed_time":0.505881477,"remaining_time":6.239204883},
{"learn":[2.227846797],"iteration":75,"passed_time":0.5094469846,"remaining_time":6.193802813},
{"learn":[2.223762878],"iteration":76,"passed_time":0.5123048538,"remaining_time":6.141004936},
{"learn":[2.217865837],"iteration":77,"passed_time":0.5153311934,"remaining_time":6.091478979},
{"learn":[2.212561363],"iteration":78,"passed_time":0.5181017928,"remaining_time":6.040148749},
{"learn":[2.20792713],"iteration":79,"passed_time":0.5216067626,"remaining_time":5.99847777},
{"learn":[2.202974819],"iteration":80,"passed_time":0.5246710756,"remaining_time":5.95274961},
{"learn":[2.197025273],"iteration":81,"passed_time":0.5273943242,"remaining_time":5.904243775},
{"learn":[2.193306146],"iteration":82,"passed_time":0.5303144057,"remaining_time":5.859015783},
{"learn":[2.189017654],"iteration":83,"passed_time":0.5329255644,"remaining_time":5.811426392},
{"learn":[2.184582939],"iteration":84,"passed_time":0.537205182,"remaining_time":5.782855782},
{"learn":[2.180734323],"iteration":85,"passed_time":0.5399742064,"remaining_time":5.738795636},
{"learn":[2.17760115],"iteration":86,"passed_time":0.5427808711,"remaining_time":5.696079716},
{"learn":[2.173050212],"iteration":87,"passed_time":0.5460946459,"remaining_time":5.65952633},
{"learn":[2.169389727],"iteration":88,"passed_time":0.5488249873,"remaining_time":5.617747904},
{"learn":[2.165298782],"iteration":89,"passed_time":0.5529568279,"remaining_time":5.591007926},
{"learn":[2.161000011],"iteration":90,"passed_time":0.5557576096,"remaining_time":5.551468869},
{"learn":[2.157521727],"iteration":91,"passed_time":0.5584699815,"remaining_time":5.511855905},
{"learn":[2.154871967],"iteration":92,"passed_time":0.5615345439,"remaining_time":5.476471305},
{"learn":[2.151504649],"iteration":93,"passed_time":0.5644292968,"remaining_time":5.440137691},
{"learn":[2.148288055],"iteration":94,"passed_time":0.5681626122,"remaining_time":5.412496463},
{"learn":[2.143002869],"iteration":95,"passed_time":0.571024068,"remaining_time":5.377143307},
{"learn":[2.140843287],"iteration":96,"passed_time":0.57384309,"remaining_time":5.342065054},
{"learn":[2.138090155],"iteration":97,"passed_time":0.5768062009,"remaining_time":5.308971359},
{"learn":[2.134541054],"iteration":98,"passed_time":0.5796509056,"remaining_time":5.275408747},
{"learn":[2.130801494],"iteration":99,"passed_time":0.5835971564,"remaining_time":5.252374408},
{"learn":[2.127839124],"iteration":100,"passed_time":0.5866462327,"remaining_time":5.221732309},
{"learn":[2.12446445],"iteration":101,"passed_time":0.589817248,"remaining_time":5.192704791},
{"learn":[2.121044561],"iteration":102,"passed_time":0.5929668898,"remaining_time":5.163993205},
{"learn":[2.118084965],"iteration":103,"passed_time":0.5975423985,"remaining_time":5.148057587},
{"learn":[2.114884866],"iteration":104,"passed_time":0.6010285274,"remaining_time":5.123052686},
{"learn":[2.110675224],"iteration":105,"passed_time":0.6041263893,"remaining_time":5.09517917},
{"learn":[2.107991766],"iteration":106,"passed_time":0.6067156281,"remaining_time":5.063523887},
{"learn":[2.10457777],"iteration":107,"passed_time":0.6103578077,"remaining_time":5.041103375},
{"learn":[2.101268111],"iteration":108,"passed_time":0.6143404574,"remaining_time":5.021810528},
{"learn":[2.098823283],"iteration":109,"passed_time":0.6179147863,"remaining_time":4.999492362},
{"learn":[2.095327382],"iteration":110,"passed_time":0.620443147,"remaining_time":4.969134754},
{"learn":[2.092775239],"iteration":111,"passed_time":0.6229942749,"remaining_time":4.939454608},
{"learn":[2.089776931],"iteration":112,"passed_time":0.6262575203,"remaining_time":4.915844429},
{"learn":[2.087850973],"iteration":113,"passed_time":0.6289563842,"remaining_time":4.888204881},
{"learn":[2.083584088],"iteration":114,"passed_time":0.6313699696,"remaining_time":4.858803679},
{"learn":[2.080535434],"iteration":115,"passed_time":0.6339182995,"remaining_time":4.830894627},
{"learn":[2.078346485],"iteration":116,"passed_time":0.6364328036,"remaining_time":4.803163808},
{"learn":[2.075102481],"iteration":117,"passed_time":0.6388702458,"remaining_time":4.77528438},
{"learn":[2.072211734],"iteration":118,"passed_time":0.6426855951,"remaining_time":4.758033691},
{"learn":[2.069188636],"iteration":119,"passed_time":0.6463054175,"remaining_time":4.739573062},
{"learn":[2.066257104],"iteration":120,"passed_time":0.6488317374,"remaining_time":4.713414026},
{"learn":[2.06310852],"iteration":121,"passed_time":0.651413613,"remaining_time":4.688042231},
{"learn":[2.060668956],"iteration":122,"passed_time":0.65389876,"remaining_time":4.662351321},
{"learn":[2.06007118],"iteration":123,"passed_time":0.6577472373,"remaining_time":4.646665967},
{"learn":[2.057579117],"iteration":124,"passed_time":0.6602572575,"remaining_time":4.621800803},
{"learn":[2.05512575],"iteration":125,"passed_time":0.6627103745,"remaining_time":4.596895773},
{"learn":[2.053150585],"iteration":126,"passed_time":0.6652196882,"remaining_time":4.572730613},
{"learn":[2.051218606],"iteration":127,"passed_time":0.6679464084,"remaining_time":4.550384907},
{"learn":[2.049346663],"iteration":128,"passed_time":0.6706063196,"remaining_time":4.527892282},
{"learn":[2.046734162],"iteration":129,"passed_time":0.6738616558,"remaining_time":4.509689543},
{"learn":[2.04396757],"iteration":130,"passed_time":0.6765804929,"remaining_time":4.488156094},
{"learn":[2.041650583],"iteration":131,"passed_time":0.6791262525,"remaining_time":4.4657696},
{"learn":[2.038332202],"iteration":132,"passed_time":0.6817700161,"remaining_time":4.444320331},
{"learn":[2.036370445],"iteration":133,"passed_time":0.6841823968,"remaining_time":4.421656386},
{"learn":[2.03411455],"iteration":134,"passed_time":0.6878973066,"remaining_time":4.407638298},
{"learn":[2.03099314],"iteration":135,"passed_time":0.6907927161,"remaining_time":4.388565491},
{"learn":[2.028864442],"iteration":136,"passed_time":0.6934907052,"remaining_time":4.368485245},
{"learn":[2.025326364],"iteration":137,"passed_time":0.696428403,"remaining_time":4.350154227},
{"learn":[2.023582226],"iteration":138,"passed_time":0.6993508102,"remaining_time":4.331949983},
{"learn":[2.021579508],"iteration":139,"passed_time":0.7028310557,"remaining_time":4.317390771},
{"learn":[2.019853177],"iteration":140,"passed_time":0.7055177787,"remaining_time":4.298154411},
{"learn":[2.018064146],"iteration":141,"passed_time":0.7083195249,"remaining_time":4.279846143},
{"learn":[2.015730845],"iteration":142,"passed_time":0.7109756418,"remaining_time":4.260881993},
{"learn":[2.014760436],"iteration":143,"passed_time":0.713875588,"remaining_time":4.243593773},
{"learn":[2.011702015],"iteration":144,"passed_time":0.7173642739,"remaining_time":4.229975546},
{"learn":[2.011328086],"iteration":145,"passed_time":0.7194341184,"remaining_time":4.208196829},
{"learn":[2.00941192],"iteration":146,"passed_time":0.7222383093,"remaining_time":4.190947468},
{"learn":[2.006826689],"iteration":147,"passed_time":0.7249516397,"remaining_time":4.17337025},
{"learn":[2.005016754],"iteration":148,"passed_time":0.7279142581,"remaining_time":4.157416333},
{"learn":[2.002743553],"iteration":149,"passed_time":0.7317386629,"remaining_time":4.14651909},
{"learn":[2.000160495],"iteration":150,"passed_time":0.7347638904,"remaining_time":4.131222139},
{"learn":[1.997700595],"iteration":151,"passed_time":0.7375778072,"remaining_time":4.114907767},
{"learn":[1.996154504],"iteration":152,"passed_time":0.7403257013,"remaining_time":4.098404373},
{"learn":[1.994316513],"iteration":153,"passed_time":0.7434906835,"remaining_time":4.084370898},
{"learn":[1.991565689],"iteration":154,"passed_time":0.7649575777,"remaining_time":4.170252601},
{"learn":[1.988083997],"iteration":155,"passed_time":0.7680901687,"remaining_time":4.155564759},
{"learn":[1.986245131],"iteration":156,"passed_time":0.7714733589,"remaining_time":4.142369691},
{"learn":[1.984331898],"iteration":157,"passed_time":0.7747631119,"remaining_time":4.128800887},
{"learn":[1.984012698],"iteration":158,"passed_time":0.7789708379,"remaining_time":4.120216822},
{"learn":[1.983691992],"iteration":159,"passed_time":0.7820521965,"remaining_time":4.105774032},
{"learn":[1.980115506],"iteration":160,"passed_time":0.78598194,"remaining_time":4.095893464},
{"learn":[1.978558571],"iteration":161,"passed_time":0.7894218641,"remaining_time":4.083552606},
{"learn":[1.976723046],"iteration":162,"passed_time":0.7935707688,"remaining_time":4.074961555},
{"learn":[1.976437554],"iteration":163,"passed_time":0.7964620662,"remaining_time":4.060013947},
{"learn":[1.974220301],"iteration":164,"passed_time":0.7998725817,"remaining_time":4.047840034},
{"learn":[1.969501611],"iteration":165,"passed_time":0.8031444618,"remaining_time":4.035075187},
{"learn":[1.968034781],"iteration":166,"passed_time":0.8064669477,"remaining_time":4.022676452},
{"learn":[1.966306564],"iteration":167,"passed_time":0.8103478489,"remaining_time":4.013151252},
{"learn":[1.963413938],"iteration":168,"passed_time":0.8136797904,"remaining_time":4.000993525},
{"learn":[1.96195],"iteration":169,"passed_time":0.81638175,"remaining_time":3.985863838},
{"learn":[1.961147722],"iteration":170,"passed_time":0.8193794721,"remaining_time":3.972313347},
{"learn":[1.959424689],"iteration":171,"passed_time":0.8227667197,"remaining_time":3.960760721},
{"learn":[1.957789412],"iteration":172,"passed_time":0.8260610371,"remaining_time":3.948858253},
{"learn":[1.955209309],"iteration":173,"passed_time":0.8291420843,"remaining_time":3.936042308},
{"learn":[1.953933191],"iteration":174,"passed_time":0.8319374546,"remaining_time":3.921990857},
{"learn":[1.952287067],"iteration":175,"passed_time":0.8354232463,"remaining_time":3.911299744},
{"learn":[1.95070758],"iteration":176,"passed_time":0.8392680509,"remaining_time":3.902359355},
{"learn":[1.94798374],"iteration":177,"passed_time":0.8422838511,"remaining_time":3.889647896},
{"learn":[1.946255926],"iteration":178,"passed_time":0.8450403251,"remaining_time":3.875855346},
{"learn":[1.945122044],"iteration":179,"passed_time":0.8478670941,"remaining_time":3.862505651},
{"learn":[1.94488382],"iteration":180,"passed_time":0.8504669778,"remaining_time":3.848245607},
{"learn":[1.944225299],"iteration":181,"passed_time":0.8545495605,"remaining_time":3.840777695},
{"learn":[1.94231387],"iteration":182,"passed_time":0.857616574,"remaining_time":3.828812792},
{"learn":[1.940518279],"iteration":183,"passed_time":0.8603210565,"remaining_time":3.815336859},
{"learn":[1.939791471],"iteration":184,"passed_time":0.8633804075,"remaining_time":3.803540714},
{"learn":[1.938020951],"iteration":185,"passed_time":0.8666026048,"remaining_time":3.792551184},
{"learn":[1.936441822],"iteration":186,"passed_time":0.869967399,"remaining_time":3.782264681},
{"learn":[1.936120287],"iteration":187,"passed_time":0.8727453672,"remaining_time":3.769517224},
{"learn":[1.93591129],"iteration":188,"passed_time":0.875322058,"remaining_time":3.756011582},
{"learn":[1.935326516],"iteration":189,"passed_time":0.8780993607,"remaining_time":3.743476222},
{"learn":[1.935135318],"iteration":190,"passed_time":0.8801528053,"remaining_time":3.727977065},
{"learn":[1.93494926],"iteration":191,"passed_time":0.8823853464,"remaining_time":3.713371666},
{"learn":[1.934098977],"iteration":192,"passed_time":0.8856113903,"remaining_time":3.703048663},
{"learn":[1.933307938],"iteration":193,"passed_time":0.8884977149,"remaining_time":3.691387413},
{"learn":[1.931851698],"iteration":194,"passed_time":0.8913669596,"remaining_time":3.679745654},
{"learn":[1.930339264],"iteration":195,"passed_time":0.8943920399,"remaining_time":3.668832653},
{"learn":[1.92905342],"iteration":196,"passed_time":0.8982830243,"remaining_time":3.661529282},
{"learn":[1.928170567],"iteration":197,"passed_time":0.9013429483,"remaining_time":3.650894164},
{"learn":[1.927334964],"iteration":198,"passed_time":0.9040636684,"remaining_time":3.638969841},
{"learn":[1.925970308],"iteration":199,"passed_time":0.9068819235,"remaining_time":3.627527694},
{"learn":[1.92450985],"iteration":200,"passed_time":0.9097769588,"remaining_time":3.616476568},
{"learn":[1.924353802],"iteration":201,"passed_time":0.9134712986,"remaining_time":3.608663843},
{"learn":[1.922623109],"iteration":202,"passed_time":0.9167759229,"remaining_time":3.599361628},
{"learn":[1.920800397],"iteration":203,"passed_time":0.9200867927,"remaining_time":3.590142583},
{"learn":[1.92064871],"iteration":204,"passed_time":0.9231895118,"remaining_time":3.580173961},
{"learn":[1.918776637],"iteration":205,"passed_time":0.9297325558,"remaining_time":3.583532278},
{"learn":[1.917074291],"iteration":206,"passed_time":0.9335467813,"remaining_time":3.576341051},
{"learn":[1.915946014],"iteration":207,"passed_time":0.9367385129,"remaining_time":3.56681203},
{"learn":[1.913685508],"iteration":208,"passed_time":0.9399452169,"remaining_time":3.557400318},
{"learn":[1.911270274],"iteration":209,"passed_time":0.9442718456,"remaining_time":3.552260752},
{"learn":[1.910801234],"iteration":210,"passed_time":0.9477099928,"remaining_time":3.543806561},
{"learn":[1.910678249],"iteration":211,"passed_time":0.9493353387,"remaining_time":3.528661542},
{"learn":[1.91052872],"iteration":212,"passed_time":0.9522607499,"remaining_time":3.518446996},
{"learn":[1.908217529],"iteration":213,"passed_time":0.9562112074,"remaining_time":3.512065463},
{"learn":[1.906893712],"iteration":214,"passed_time":0.9612044192,"remaining_time":3.50951381},
{"learn":[1.906335248],"iteration":215,"passed_time":0.9644948256,"remaining_time":3.500758997},
{"learn":[1.903613595],"iteration":216,"passed_time":0.9678353856,"remaining_time":3.492235516},
{"learn":[1.903444185],"iteration":217,"passed_time":0.9718436698,"remaining_time":3.486154816},
{"learn":[1.901830057],"iteration":218,"passed_time":0.97566647,"remaining_time":3.479431567},
{"learn":[1.900388229],"iteration":219,"passed_time":0.9789745007,"remaining_time":3.470909593},
{"learn":[1.897980407],"iteration":220,"passed_time":0.9821470594,"remaining_time":3.461957282},
{"learn":[1.896068063],"iteration":221,"passed_time":0.9862408704,"remaining_time":3.456285573},
{"learn":[1.894509137],"iteration":222,"passed_time":0.9899588996,"remaining_time":3.449318677},
{"learn":[1.893255673],"iteration":223,"passed_time":0.992990346,"remaining_time":3.44000227},
{"learn":[1.892199809],"iteration":224,"passed_time":0.9961218067,"remaining_time":3.431086223},
{"learn":[1.891287058],"iteration":225,"passed_time":0.9995701329,"remaining_time":3.423306561},
{"learn":[1.889226187],"iteration":226,"passed_time":1.004141678,"remaining_time":3.419389942},
{"learn":[1.888862517],"iteration":227,"passed_time":1.007183147,"remaining_time":3.410286795},
{"learn":[1.888748102],"iteration":228,"passed_time":1.010052672,"remaining_time":3.400657685},
{"learn":[1.886718135],"iteration":229,"passed_time":1.013373715,"remaining_time":3.392598961},
{"learn":[1.885604057],"iteration":230,"passed_time":1.017277049,"remaining_time":3.386519701},
{"learn":[1.885288834],"iteration":231,"passed_time":1.021040218,"remaining_time":3.379995204},
{"learn":[1.884009652],"iteration":232,"passed_time":1.030932726,"remaining_time":3.393671247},
{"learn":[1.882993847],"iteration":233,"passed_time":1.039206971,"remaining_time":3.40184846},
{"learn":[1.881151045],"iteration":234,"passed_time":1.049496764,"remaining_time":3.416446912},
{"learn":[1.880381136],"iteration":235,"passed_time":1.058628717,"remaining_time":3.427086185},
{"learn":[1.880278658],"iteration":236,"passed_time":1.066968083,"remaining_time":3.43500695},
{"learn":[1.8786769],"iteration":237,"passed_time":1.076811303,"remaining_time":3.447605935},
{"learn":[1.877480114],"iteration":238,"passed_time":1.085691874,"remaining_time":3.456951949},
{"learn":[1.875455651],"iteration":239,"passed_time":1.095721908,"remaining_time":3.469786043},
{"learn":[1.874230652],"iteration":240,"passed_time":1.105499987,"remaining_time":3.481636889},
{"learn":[1.871869254],"iteration":241,"passed_time":1.114601288,"remaining_time":3.491189159},
{"learn":[1.870691806],"iteration":242,"passed_time":1.124780354,"remaining_time":3.503945384},
{"learn":[1.8692165],"iteration":243,"passed_time":1.134234477,"remaining_time":3.514267478},
{"learn":[1.867414779],"iteration":244,"passed_time":1.142983266,"remaining_time":3.522254554},
{"learn":[1.865862056],"iteration":245,"passed_time":1.153489913,"remaining_time":3.535493473},
{"learn":[1.863988871],"iteration":246,"passed_time":1.163603332,"remaining_time":3.547341332},
{"learn":[1.862738576],"iteration":247,"passed_time":1.174244573,"remaining_time":3.560612576},
{"learn":[1.861064917],"iteration":248,"passed_time":1.184814686,"remaining_time":3.573477224},
{"learn":[1.859310351],"iteration":249,"passed_time":1.199512891,"remaining_time":3.598538672},
{"learn":[1.857327835],"iteration":250,"passed_time":1.208266263,"remaining_time":3.605543549},
{"learn":[1.855965656],"iteration":251,"passed_time":1.219602249,"remaining_time":3.620089217},
{"learn":[1.855867291],"iteration":252,"passed_time":1.232875233,"remaining_time":3.640149403},
{"learn":[1.854921724],"iteration":253,"passed_time":1.244424896,"remaining_time":3.654885718},
{"learn":[1.852860144],"iteration":254,"passed_time":1.255784438,"remaining_time":3.668860416},
{"learn":[1.851114111],"iteration":255,"passed_time":1.301661211,"remaining_time":3.782952894},
{"learn":[1.849277749],"iteration":256,"passed_time":1.32080275,"remaining_time":3.81850756},
{"learn":[1.847809249],"iteration":257,"passed_time":1.326874684,"remaining_time":3.816050447},
{"learn":[1.846572242],"iteration":258,"passed_time":1.331913944,"remaining_time":3.810610938},
{"learn":[1.844501647],"iteration":259,"passed_time":1.336825639,"remaining_time":3.804811435},
{"learn":[1.843021368],"iteration":260,"passed_time":1.341755623,"remaining_time":3.799070518},
{"learn":[1.841416435],"iteration":261,"passed_time":1.344807388,"remaining_time":3.788045237},
{"learn":[1.840670038],"iteration":262,"passed_time":1.353619366,"remaining_time":3.793222331},
{"learn":[1.839106228],"iteration":263,"passed_time":1.357709316,"remaining_time":3.785129003},
{"learn":[1.837607506],"iteration":264,"passed_time":1.361995,"remaining_time":3.777608774},
{"learn":[1.83618406],"iteration":265,"passed_time":1.36476898,"remaining_time":3.765941472},
{"learn":[1.835985366],"iteration":266,"passed_time":1.367578903,"remaining_time":3.754439461},
{"learn":[1.834978251],"iteration":267,"passed_time":1.370577428,"remaining_time":3.743517454},
{"learn":[1.834154317],"iteration":268,"passed_time":1.373253728,"remaining_time":3.731778717},
{"learn":[1.833283452],"iteration":269,"passed_time":1.378233864,"remaining_time":3.726336002},
{"learn":[1.832365374],"iteration":270,"passed_time":1.381334728,"remaining_time":3.71584139},
{"learn":[1.828406164],"iteration":271,"passed_time":1.384385661,"remaining_time":3.705267504},
{"learn":[1.825465739],"iteration":272,"passed_time":1.387380904,"remaining_time":3.69460043},
{"learn":[1.824203117],"iteration":273,"passed_time":1.390954358,"remaining_time":3.685521402},
{"learn":[1.823630731],"iteration":274,"passed_time":1.394151532,"remaining_time":3.675490404},
{"learn":[1.82255173],"iteration":275,"passed_time":1.396765796,"remaining_time":3.663979843},
{"learn":[1.820649127],"iteration":276,"passed_time":1.399384211,"remaining_time":3.652544347},
{"learn":[1.818999588],"iteration":277,"passed_time":1.402337143,"remaining_time":3.642041068},
{"learn":[1.817567185],"iteration":278,"passed_time":1.405947021,"remaining_time":3.633289612},
{"learn":[1.816301771],"iteration":279,"passed_time":1.409049801,"remaining_time":3.623270917},
{"learn":[1.814288208],"iteration":280,"passed_time":1.411864205,"remaining_time":3.61256357},
{"learn":[1.813196518],"iteration":281,"passed_time":1.414504905,"remaining_time":3.601469936},
{"learn":[1.813035797],"iteration":282,"passed_time":1.417058835,"remaining_time":3.590216201},
{"learn":[1.812656167],"iteration":283,"passed_time":1.420422483,"remaining_time":3.581065134},
{"learn":[1.811531557],"iteration":284,"passed_time":1.423460582,"remaining_time":3.571137952},
{"learn":[1.811472967],"iteration":285,"passed_time":1.425930607,"remaining_time":3.559840746},
{"learn":[1.809817435],"iteration":286,"passed_time":1.428666567,"remaining_time":3.549265723},
{"learn":[1.808005254],"iteration":287,"passed_time":1.431575824,"remaining_time":3.539173565},
{"learn":[1.806436325],"iteration":288,"passed_time":1.434303484,"remaining_time":3.528684349},
{"learn":[1.80583425],"iteration":289,"passed_time":1.437598722,"remaining_time":3.519638251},
{"learn":[1.804237793],"iteration":290,"passed_time":1.440698263,"remaining_time":3.510154874},
{"learn":[1.803721214],"iteration":291,"passed_time":1.44370254,"remaining_time":3.500484241},
{"learn":[1.803359073],"iteration":292,"passed_time":1.446952476,"remaining_time":3.49145188},
{"learn":[1.801320866],"iteration":293,"passed_time":1.461289616,"remaining_time":3.509083228},
{"learn":[1.800327351],"iteration":294,"passed_time":1.464798626,"remaining_time":3.500620445},
{"learn":[1.800032047],"iteration":295,"passed_time":1.468511339,"remaining_time":3.492675617},
{"learn":[1.798711729],"iteration":296,"passed_time":1.471743248,"remaining_time":3.483621224},
{"learn":[1.797555121],"iteration":297,"passed_time":1.474841238,"remaining_time":3.474290433},
{"learn":[1.795786272],"iteration":298,"passed_time":1.478110349,"remaining_time":3.465402525},
{"learn":[1.795494478],"iteration":299,"passed_time":1.483019987,"remaining_time":3.460379969},
{"learn":[1.793464079],"iteration":300,"passed_time":1.486301671,"remaining_time":3.451577634},
{"learn":[1.791207565],"iteration":301,"passed_time":1.489278513,"remaining_time":3.442107291},
{"learn":[1.791155075],"iteration":302,"passed_time":1.492728448,"remaining_time":3.433768081},
{"learn":[1.79008659],"iteration":303,"passed_time":1.49840767,"remaining_time":3.430564928},
{"learn":[1.788836409],"iteration":304,"passed_time":1.501690983,"remaining_time":3.42188601},
{"learn":[1.787508291],"iteration":305,"passed_time":1.504710277,"remaining_time":3.41264357},
{"learn":[1.783882514],"iteration":306,"passed_time":1.508269536,"remaining_time":3.404660549},
{"learn":[1.782651183],"iteration":307,"passed_time":1.513369218,"remaining_time":3.400167203},
{"learn":[1.780383446],"iteration":308,"passed_time":1.516656539,"remaining_time":3.391617051},
{"learn":[1.778885995],"iteration":309,"passed_time":1.519918281,"remaining_time":3.383043917},
{"learn":[1.778833835],"iteration":310,"passed_time":1.52311772,"remaining_time":3.374366909},
{"learn":[1.775442186],"iteration":311,"passed_time":1.527864606,"remaining_time":3.369137337},
{"learn":[1.773803509],"iteration":312,"passed_time":1.531075337,"remaining_time":3.360539158},
{"learn":[1.772719093],"iteration":313,"passed_time":1.534177023,"remaining_time":3.351737063},
{"learn":[1.771458773],"iteration":314,"passed_time":1.538215121,"remaining_time":3.345007486},
{"learn":[1.770561104],"iteration":315,"passed_time":1.542991417,"remaining_time":3.339892815},
{"learn":[1.769283162],"iteration":316,"passed_time":1.546312344,"remaining_time":3.331644577},
{"learn":[1.769233376],"iteration":317,"passed_time":1.549173369,"remaining_time":3.322440998},
{"learn":[1.767984277],"iteration":318,"passed_time":1.552504107,"remaining_time":3.314279928},
{"learn":[1.767394193],"iteration":319,"passed_time":1.557305255,"remaining_time":3.309273668},
{"learn":[1.767284837],"iteration":320,"passed_time":1.560886404,"remaining_time":3.301688062},
{"learn":[1.765634166],"iteration":321,"passed_time":1.564461822,"remaining_time":3.294115265},
{"learn":[1.762453672],"iteration":322,"passed_time":1.56800999,"remaining_time":3.286510102},
{"learn":[1.762409762],"iteration":323,"passed_time":1.573263263,"remaining_time":3.28248755},
{"learn":[1.761741757],"iteration":324,"passed_time":1.576759143,"remaining_time":3.274807451},
{"learn":[1.760738256],"iteration":325,"passed_time":1.580515892,"remaining_time":3.267692367},
{"learn":[1.759461259],"iteration":326,"passed_time":1.584285516,"remaining_time":3.260624318},
{"learn":[1.759418651],"iteration":327,"passed_time":1.58856285,"remaining_time":3.25461657},
{"learn":[1.758027604],"iteration":328,"passed_time":1.592065874,"remaining_time":3.247040125},
{"learn":[1.757335883],"iteration":329,"passed_time":1.595236874,"remaining_time":3.23881426},
{"learn":[1.756165529],"iteration":330,"passed_time":1.598336461,"remaining_time":3.2304746},
{"learn":[1.754470407],"iteration":331,"passed_time":1.60339194,"remaining_time":3.226101856},
{"learn":[1.753575862],"iteration":332,"passed_time":1.606895567,"remaining_time":3.218616646},
{"learn":[1.751982145],"iteration":333,"passed_time":1.610105282,"remaining_time":3.210569214},
{"learn":[1.749397176],"iteration":334,"passed_time":1.613400305,"remaining_time":3.202720008},
{"learn":[1.748263645],"iteration":335,"passed_time":1.619513101,"remaining_time":3.200466366},
{"learn":[1.747823151],"iteration":336,"passed_time":1.623284659,"remaining_time":3.193583765},
{"learn":[1.745704969],"iteration":337,"passed_time":1.626400002,"remaining_time":3.185434324},
{"learn":[1.745373808],"iteration":338,"passed_time":1.629798942,"remaining_time":3.177867553},
{"learn":[1.74392763],"iteration":339,"passed_time":1.634671125,"remaining_time":3.173185125},
{"learn":[1.742905773],"iteration":340,"passed_time":1.638238299,"remaining_time":3.165979586},
{"learn":[1.73985901],"iteration":341,"passed_time":1.641364341,"remaining_time":3.157946598},
{"learn":[1.739074601],"iteration":342,"passed_time":1.644683783,"remaining_time":3.150312668},
{"learn":[1.737987176],"iteration":343,"passed_time":1.649375723,"remaining_time":3.145321146},
{"learn":[1.73620774],"iteration":344,"passed_time":1.652809666,"remaining_time":3.137942989},
{"learn":[1.73550382],"iteration":345,"passed_time":1.656275736,"remaining_time":3.130648357},
{"learn":[1.733429607],"iteration":346,"passed_time":1.659788358,"remaining_time":3.123463394},
{"learn":[1.732438249],"iteration":347,"passed_time":1.664820858,"remaining_time":3.119147125},
{"learn":[1.730814462],"iteration":348,"passed_time":1.668248603,"remaining_time":3.111833353},
{"learn":[1.730229804],"iteration":349,"passed_time":1.671471618,"remaining_time":3.104161577},
{"learn":[1.729495768],"iteration":350,"passed_time":1.67507985,"remaining_time":3.097227415},
{"learn":[1.728059059],"iteration":351,"passed_time":1.679523725,"remaining_time":3.091850493},
{"learn":[1.727104475],"iteration":352,"passed_time":1.683156674,"remaining_time":3.084992544},
{"learn":[1.725782181],"iteration":353,"passed_time":1.686459375,"remaining_time":3.077550159},
{"learn":[1.72495131],"iteration":354,"passed_time":1.690221385,"remaining_time":3.070965616},
{"learn":[1.723984639],"iteration":355,"passed_time":1.695056416,"remaining_time":3.066338011},
{"learn":[1.723188585],"iteration":356,"passed_time":1.69862757,"remaining_time":3.05943285},
{"learn":[1.72091276],"iteration":357,"passed_time":1.702299664,"remaining_time":3.05272733},
{"learn":[1.71967487],"iteration":358,"passed_time":1.705994295,"remaining_time":3.046078951},
{"learn":[1.71806028],"iteration":359,"passed_time":1.71040353,"remaining_time":3.040717386},
{"learn":[1.716185865],"iteration":360,"passed_time":1.714400648,"remaining_time":3.034631619},
{"learn":[1.715398141],"iteration":361,"passed_time":1.718229327,"remaining_time":3.028260527},
{"learn":[1.713781743],"iteration":362,"passed_time":1.721814895,"remaining_time":3.021476826},
{"learn":[1.71271742],"iteration":363,"passed_time":1.726280671,"remaining_time":3.016248644},
{"learn":[1.712622244],"iteration":364,"passed_time":1.729713458,"remaining_time":3.009227524},
{"learn":[1.711912244],"iteration":365,"passed_time":1.733122034,"remaining_time":3.002184069},
{"learn":[1.711177117],"iteration":366,"passed_time":1.738418918,"remaining_time":2.99841737},
{"learn":[1.710402376],"iteration":367,"passed_time":1.74206949,"remaining_time":2.991814993},
{"learn":[1.708959521],"iteration":368,"passed_time":1.746081225,"remaining_time":2.985846214},
{"learn":[1.707968235],"iteration":369,"passed_time":1.749482296,"remaining_time":2.978848233},
{"learn":[1.706832236],"iteration":370,"passed_time":1.754841794,"remaining_time":2.975189996},
{"learn":[1.706238911],"iteration":371,"passed_time":1.758489001,"remaining_time":2.96863197},
{"learn":[1.705001562],"iteration":372,"passed_time":1.761912804,"remaining_time":2.961714016},
{"learn":[1.703771794],"iteration":373,"passed_time":1.765811943,"remaining_time":2.955610365},
{"learn":[1.703234303],"iteration":374,"passed_time":1.770493061,"remaining_time":2.950821769},
{"learn":[1.702394745],"iteration":375,"passed_time":1.774139587,"remaining_time":2.944316762},
{"learn":[1.701537668],"iteration":376,"passed_time":1.777740274,"remaining_time":2.937751169},
{"learn":[1.700400373],"iteration":377,"passed_time":1.781214058,"remaining_time":2.930992444},
{"learn":[1.69979935],"iteration":378,"passed_time":1.78614737,"remaining_time":2.926642525},
{"learn":[1.698473548],"iteration":379,"passed_time":1.789963599,"remaining_time":2.920466924},
{"learn":[1.697403683],"iteration":380,"passed_time":1.793628256,"remaining_time":2.914057455},
{"learn":[1.696330697],"iteration":381,"passed_time":1.797848547,"remaining_time":2.908561262},
{"learn":[1.695434543],"iteration":382,"passed_time":1.801930678,"remaining_time":2.90284916},
{"learn":[1.694804908],"iteration":383,"passed_time":1.805676091,"remaining_time":2.896605396},
{"learn":[1.694257608],"iteration":384,"passed_time":1.809142866,"remaining_time":2.889929513},
{"learn":[1.694243415],"iteration":385,"passed_time":1.811383053,"remaining_time":2.881319156},
{"learn":[1.691301398],"iteration":386,"passed_time":1.815934096,"remaining_time":2.876402069},
{"learn":[1.689790433],"iteration":387,"passed_time":1.819617873,"remaining_time":2.870118913},
{"learn":[1.688383799],"iteration":388,"passed_time":1.823205296,"remaining_time":2.863697778},
{"learn":[1.687677019],"iteration":389,"passed_time":1.827327924,"remaining_time":2.858128291},
{"learn":[1.687333548],"iteration":390,"passed_time":1.831685513,"remaining_time":2.852932167},
{"learn":[1.686097587],"iteration":391,"passed_time":1.835863543,"remaining_time":2.847461821},
{"learn":[1.685302517],"iteration":392,"passed_time":1.83946606,"remaining_time":2.841109157},
{"learn":[1.68430924],"iteration":393,"passed_time":1.844642455,"remaining_time":2.837191186},
{"learn":[1.682764123],"iteration":394,"passed_time":1.848175458,"remaining_time":2.830749752},
{"learn":[1.681825211],"iteration":395,"passed_time":1.852058474,"remaining_time":2.824856864},
{"learn":[1.680972091],"iteration":396,"passed_time":1.855973596,"remaining_time":2.819022868},
{"learn":[1.680302367],"iteration":397,"passed_time":1.861718305,"remaining_time":2.815965878},
{"learn":[1.679599333],"iteration":398,"passed_time":1.86542993,"remaining_time":2.809833052},
{"learn":[1.679074864],"iteration":399,"passed_time":1.869029984,"remaining_time":2.803544975},
{"learn":[1.677071234],"iteration":400,"passed_time":1.87316821,"remaining_time":2.798074209},
{"learn":[1.675860626],"iteration":401,"passed_time":1.87779381,"remaining_time":2.793335071},
{"learn":[1.675176497],"iteration":402,"passed_time":1.881721704,"remaining_time":2.787562921},
{"learn":[1.675163891],"iteration":403,"passed_time":1.884242689,"remaining_time":2.779724363},
{"learn":[1.674159983],"iteration":404,"passed_time":1.888570019,"remaining_time":2.77456583},
{"learn":[1.674148213],"iteration":405,"passed_time":1.891041439,"remaining_time":2.766696096},
{"learn":[1.672967504],"iteration":406,"passed_time":1.894363563,"remaining_time":2.760092366},
{"learn":[1.67228413],"iteration":407,"passed_time":1.898518393,"remaining_time":2.754712963},
{"learn":[1.671772712],"iteration":408,"passed_time":1.902957107,"remaining_time":2.749749755},
{"learn":[1.670466224],"iteration":409,"passed_time":1.906674169,"remaining_time":2.743750633},
{"learn":[1.669290345],"iteration":410,"passed_time":1.910028644,"remaining_time":2.737242996},
{"learn":[1.667756891],"iteration":411,"passed_time":1.913993662,"remaining_time":2.731622023},
{"learn":[1.66669363],"iteration":412,"passed_time":1.918654465,"remaining_time":2.726997992},
{"learn":[1.666332796],"iteration":413,"passed_time":1.922114978,"remaining_time":2.720674824},
{"learn":[1.665675014],"iteration":414,"passed_time":1.925757019,"remaining_time":2.71462134},
{"learn":[1.664716733],"iteration":415,"passed_time":1.930923936,"remaining_time":2.710720141},
{"learn":[1.663843201],"iteration":416,"passed_time":1.934859615,"remaining_time":2.7050915},
{"learn":[1.663016101],"iteration":417,"passed_time":1.938341211,"remaining_time":2.698838719},
{"learn":[1.66156217],"iteration":418,"passed_time":1.94224232,"remaining_time":2.693180878},
{"learn":[1.660288641],"iteration":419,"passed_time":1.946908343,"remaining_time":2.688587712},
{"learn":[1.659254229],"iteration":420,"passed_time":1.950696134,"remaining_time":2.682786369},
{"learn":[1.657544683],"iteration":421,"passed_time":1.954299205,"remaining_time":2.676741565},
{"learn":[1.656704405],"iteration":422,"passed_time":1.957864569,"remaining_time":2.67065687},
{"learn":[1.655754812],"iteration":423,"passed_time":1.962971431,"remaining_time":2.666678171},
{"learn":[1.654878682],"iteration":424,"passed_time":1.966726951,"remaining_time":2.660865875},
{"learn":[1.654688889],"iteration":425,"passed_time":1.97046264,"remaining_time":2.655036516},
{"learn":[1.652917098],"iteration":426,"passed_time":1.974614064,"remaining_time":2.649774845},
{"learn":[1.652023702],"iteration":427,"passed_time":1.979218756,"remaining_time":2.645124132},
{"learn":[1.650648814],"iteration":428,"passed_time":1.983175729,"remaining_time":2.639611518},
{"learn":[1.649928943],"iteration":429,"passed_time":1.986866133,"remaining_time":2.633752781},
{"learn":[1.64929346],"iteration":430,"passed_time":1.991956136,"remaining_time":2.629751837},
{"learn":[1.648181098],"iteration":431,"passed_time":1.995803799,"remaining_time":2.624112402},
{"learn":[1.646852103],"iteration":432,"passed_time":1.999316009,"remaining_time":2.618041979},
{"learn":[1.646421407],"iteration":433,"passed_time":2.002874204,"remaining_time":2.612043316},
{"learn":[1.645096754],"iteration":434,"passed_time":2.007628916,"remaining_time":2.607609972},
{"learn":[1.644628732],"iteration":435,"passed_time":2.011213716,"remaining_time":2.60166178},
{"learn":[1.643772771],"iteration":436,"passed_time":2.014804686,"remaining_time":2.595732354},
{"learn":[1.642816877],"iteration":437,"passed_time":2.018551605,"remaining_time":2.590013704},
{"learn":[1.641723165],"iteration":438,"passed_time":2.023520157,"remaining_time":2.585865167},
{"learn":[1.640769068],"iteration":439,"passed_time":2.027225503,"remaining_time":2.580105185},
{"learn":[1.639238802],"iteration":440,"passed_time":2.030796755,"remaining_time":2.574184549},
{"learn":[1.637568948],"iteration":441,"passed_time":2.035138938,"remaining_time":2.5692478},
{"learn":[1.636104586],"iteration":442,"passed_time":2.039389444,"remaining_time":2.564198465},
{"learn":[1.634563295],"iteration":443,"passed_time":2.043562934,"remaining_time":2.559056287},
{"learn":[1.633841485],"iteration":444,"passed_time":2.047124923,"remaining_time":2.553155803},
{"learn":[1.633526058],"iteration":445,"passed_time":2.052020919,"remaining_time":2.548922845},
{"learn":[1.631880008],"iteration":446,"passed_time":2.055965739,"remaining_time":2.543510187},
{"learn":[1.630499755],"iteration":447,"passed_time":2.059643708,"remaining_time":2.537775283},
{"learn":[1.627881723],"iteration":448,"passed_time":2.063603275,"remaining_time":2.532395111},
{"learn":[1.627110328],"iteration":449,"passed_time":2.068803287,"remaining_time":2.52853735},
{"learn":[1.626395211],"iteration":450,"passed_time":2.072549246,"remaining_time":2.522903627},
{"learn":[1.625649766],"iteration":451,"passed_time":2.075997274,"remaining_time":2.516917049},
{"learn":[1.624664295],"iteration":452,"passed_time":2.079904328,"remaining_time":2.511495955},
{"learn":[1.623700688],"iteration":453,"passed_time":2.084574782,"remaining_time":2.506999628},
{"learn":[1.623158291],"iteration":454,"passed_time":2.08814004,"remaining_time":2.501178729},
{"learn":[1.622555586],"iteration":455,"passed_time":2.091891658,"remaining_time":2.495590048},
{"learn":[1.621380945],"iteration":456,"passed_time":2.09619563,"remaining_time":2.490665704},
{"learn":[1.620999342],"iteration":457,"passed_time":2.10086497,"remaining_time":2.486176449},
{"learn":[1.620058389],"iteration":458,"passed_time":2.105092518,"remaining_time":2.481165691},
{"learn":[1.619700021],"iteration":459,"passed_time":2.108678471,"remaining_time":2.475405162},
{"learn":[1.618729827],"iteration":460,"passed_time":2.113611962,"remaining_time":2.471229604},
{"learn":[1.617477284],"iteration":461,"passed_time":2.117326182,"remaining_time":2.465630922},
{"learn":[1.616768888],"iteration":462,"passed_time":2.121250817,"remaining_time":2.460284425},
{"learn":[1.616401226],"iteration":463,"passed_time":2.124770672,"remaining_time":2.454476466},
{"learn":[1.615212],"iteration":464,"passed_time":2.129510993,"remaining_time":2.45008254},
{"learn":[1.614376693],"iteration":465,"passed_time":2.133713367,"remaining_time":2.445070682},
{"learn":[1.612954948],"iteration":466,"passed_time":2.143692524,"remaining_time":2.446655493},
{"learn":[1.610513753],"iteration":467,"passed_time":2.147144226,"remaining_time":2.440770786},
{"learn":[1.610289279],"iteration":468,"passed_time":2.150793369,"remaining_time":2.435119997},
{"learn":[1.609586204],"iteration":469,"passed_time":2.154292219,"remaining_time":2.429308247},
{"learn":[1.609344505],"iteration":470,"passed_time":2.159747224,"remaining_time":2.425703358},
{"learn":[1.608364537],"iteration":471,"passed_time":2.16359348,"remaining_time":2.420291012},
{"learn":[1.607922082],"iteration":472,"passed_time":2.167801529,"remaining_time":2.415288384},
{"learn":[1.606722821],"iteration":473,"passed_time":2.172855324,"remaining_time":2.411227638},
{"learn":[1.606077543],"iteration":474,"passed_time":2.177123784,"remaining_time":2.406294708},
{"learn":[1.604376319],"iteration":475,"passed_time":2.180590666,"remaining_time":2.400482162},
{"learn":[1.602907585],"iteration":476,"passed_time":2.184504676,"remaining_time":2.395169698},
{"learn":[1.601678318],"iteration":477,"passed_time":2.189401326,"remaining_time":2.390936176},
{"learn":[1.60114276],"iteration":478,"passed_time":2.19292312,"remaining_time":2.385204479},
{"learn":[1.600306967],"iteration":479,"passed_time":2.196369807,"remaining_time":2.379400624},
{"learn":[1.599619131],"iteration":480,"passed_time":2.200097575,"remaining_time":2.373909858},
{"learn":[1.598563548],"iteration":481,"passed_time":2.204993576,"remaining_time":2.369681893},
{"learn":[1.598018958],"iteration":482,"passed_time":2.208825658,"remaining_time":2.36431235},
{"learn":[1.596423694],"iteration":483,"passed_time":2.212404865,"remaining_time":2.358679567},
{"learn":[1.595317291],"iteration":484,"passed_time":2.216294272,"remaining_time":2.353384639},
{"learn":[1.594943318],"iteration":485,"passed_time":2.221427028,"remaining_time":2.349410478},
{"learn":[1.59341825],"iteration":486,"passed_time":2.225309579,"remaining_time":2.344114607},
{"learn":[1.592373307],"iteration":487,"passed_time":2.228811915,"remaining_time":2.338425615},
{"learn":[1.592123879],"iteration":488,"passed_time":2.234100475,"remaining_time":2.334612153},
{"learn":[1.59062729],"iteration":489,"passed_time":2.237847355,"remaining_time":2.329188063},
{"learn":[1.589549803],"iteration":490,"passed_time":2.241693571,"remaining_time":2.323873783},
{"learn":[1.588274626],"iteration":491,"passed_time":2.245257704,"remaining_time":2.318274214},
{"learn":[1.586827199],"iteration":492,"passed_time":2.25010492,"remaining_time":2.314002423},
{"learn":[1.586023943],"iteration":493,"passed_time":2.253629033,"remaining_time":2.308373059},
{"learn":[1.584007548],"iteration":494,"passed_time":2.264932365,"remaining_time":2.310688575},
{"learn":[1.582775853],"iteration":495,"passed_time":2.276126864,"remaining_time":2.312838587},
{"learn":[1.582145064],"iteration":496,"passed_time":2.286028388,"remaining_time":2.313626316},
{"learn":[1.581022775],"iteration":497,"passed_time":2.296802107,"remaining_time":2.315250317},
{"learn":[1.580238048],"iteration":498,"passed_time":2.308575583,"remaining_time":2.317828391},
{"learn":[1.579610921],"iteration":499,"passed_time":2.317809594,"remaining_time":2.317809594},
{"learn":[1.578615672],"iteration":500,"passed_time":2.328804429,"remaining_time":2.319507805},
{"learn":[1.577397123],"iteration":501,"passed_time":2.342144754,"remaining_time":2.323482246},
{"learn":[1.576209719],"iteration":502,"passed_time":2.355205281,"remaining_time":2.327111381},
{"learn":[1.573973678],"iteration":503,"passed_time":2.364825005,"remaining_time":2.3272881},
{"learn":[1.572947324],"iteration":504,"passed_time":2.375984769,"remaining_time":2.328935565},
{"learn":[1.57224989],"iteration":505,"passed_time":2.386272093,"remaining_time":2.32968066},
{"learn":[1.571523797],"iteration":506,"passed_time":2.396256009,"remaining_time":2.330087204},
{"learn":[1.571186403],"iteration":507,"passed_time":2.405975675,"remaining_time":2.330196914},
{"learn":[1.569924737],"iteration":508,"passed_time":2.417649404,"remaining_time":2.332152962},
{"learn":[1.569296742],"iteration":509,"passed_time":2.428032468,"remaining_time":2.332815508},
{"learn":[1.568507959],"iteration":510,"passed_time":2.4376354,"remaining_time":2.33268828},
{"learn":[1.567806716],"iteration":511,"passed_time":2.448563987,"remaining_time":2.33378755},
{"learn":[1.5663191],"iteration":512,"passed_time":2.460552415,"remaining_time":2.335846055},
{"learn":[1.565316529],"iteration":513,"passed_time":2.469703516,"remaining_time":2.335167137},
{"learn":[1.564311165],"iteration":514,"passed_time":2.480892387,"remaining_time":2.336374384},
{"learn":[1.563311034],"iteration":515,"passed_time":2.492489611,"remaining_time":2.337916612},
{"learn":[1.56259698],"iteration":516,"passed_time":2.500885955,"remaining_time":2.336417633},
{"learn":[1.56233754],"iteration":517,"passed_time":2.510983153,"remaining_time":2.336474671},
{"learn":[1.561369657],"iteration":518,"passed_time":2.521781835,"remaining_time":2.337142703},
{"learn":[1.560903539],"iteration":519,"passed_time":2.5311969,"remaining_time":2.336489446},
{"learn":[1.560151832],"iteration":520,"passed_time":2.541163424,"remaining_time":2.336309558},
{"learn":[1.559753499],"iteration":521,"passed_time":2.552839493,"remaining_time":2.33765762},
{"learn":[1.559379936],"iteration":522,"passed_time":2.561756701,"remaining_time":2.336439668},
{"learn":[1.557925274],"iteration":523,"passed_time":2.572755164,"remaining_time":2.337082935},
{"learn":[1.556780172],"iteration":524,"passed_time":2.585011541,"remaining_time":2.338819966},
{"learn":[1.556205249],"iteration":525,"passed_time":2.595262185,"remaining_time":2.338696341},
{"learn":[1.5552872],"iteration":526,"passed_time":2.604438348,"remaining_time":2.337569903},
{"learn":[1.553966409],"iteration":527,"passed_time":2.615385224,"remaining_time":2.337995882},
{"learn":[1.5532453],"iteration":528,"passed_time":2.625126101,"remaining_time":2.337305091},
{"learn":[1.549558951],"iteration":529,"passed_time":2.65449968,"remaining_time":2.353990283},
{"learn":[1.548853111],"iteration":530,"passed_time":2.666449647,"remaining_time":2.355112777},
{"learn":[1.547876448],"iteration":531,"passed_time":2.6788357,"remaining_time":2.356569751},
{"learn":[1.547186463],"iteration":532,"passed_time":2.693388363,"remaining_time":2.359873106},
{"learn":[1.546918314],"iteration":533,"passed_time":2.707070612,"remaining_time":2.36235001},
{"learn":[1.546912238],"iteration":534,"passed_time":2.719236292,"remaining_time":2.363448366},
{"learn":[1.54633684],"iteration":535,"passed_time":2.730077935,"remaining_time":2.363351048},
{"learn":[1.546077077],"iteration":536,"passed_time":2.741030022,"remaining_time":2.363308939},
{"learn":[1.544934757],"iteration":537,"passed_time":2.753519824,"remaining_time":2.364546764},
{"learn":[1.544722185],"iteration":538,"passed_time":2.764883903,"remaining_time":2.364770834},
{"learn":[1.544067524],"iteration":539,"passed_time":2.775802867,"remaining_time":2.364572813},
{"learn":[1.542367841],"iteration":540,"passed_time":2.786673401,"remaining_time":2.364294069},
{"learn":[1.541875136],"iteration":541,"passed_time":2.799000241,"remaining_time":2.365206845},
{"learn":[1.540481782],"iteration":542,"passed_time":2.811614352,"remaining_time":2.366312631},
{"learn":[1.537125642],"iteration":543,"passed_time":2.818464065,"remaining_time":2.362536055},
{"learn":[1.537119877],"iteration":544,"passed_time":2.844865807,"remaining_time":2.375071453},
{"learn":[1.53599829],"iteration":545,"passed_time":2.850612943,"remaining_time":2.370289883},
{"learn":[1.53598989],"iteration":546,"passed_time":2.856990577,"remaining_time":2.366026931},
{"learn":[1.535296831],"iteration":547,"passed_time":2.861765405,"remaining_time":2.360434239},
{"learn":[1.533869545],"iteration":548,"passed_time":2.866513858,"remaining_time":2.35482286},
{"learn":[1.53325752],"iteration":549,"passed_time":2.872127391,"remaining_time":2.349922411},
{"learn":[1.53232373],"iteration":550,"passed_time":2.87722198,"remaining_time":2.344596496},
{"learn":[1.531459036],"iteration":551,"passed_time":2.881515156,"remaining_time":2.338620996},
{"learn":[1.529951498],"iteration":552,"passed_time":2.884736156,"remaining_time":2.331784922},
{"learn":[1.529744894],"iteration":553,"passed_time":2.887755156,"remaining_time":2.324799278},
{"learn":[1.528850903],"iteration":554,"passed_time":2.895444697,"remaining_time":2.321572775},
{"learn":[1.527672001],"iteration":555,"passed_time":2.899517339,"remaining_time":2.315441904},
{"learn":[1.526601567],"iteration":556,"passed_time":2.902517155,"remaining_time":2.30846517},
{"learn":[1.525341224],"iteration":557,"passed_time":2.905461464,"remaining_time":2.301458722},
{"learn":[1.525336313],"iteration":558,"passed_time":2.908427802,"remaining_time":2.294484187},
{"learn":[1.525331848],"iteration":559,"passed_time":2.909984192,"remaining_time":2.286416151},
{"learn":[1.522228034],"iteration":560,"passed_time":2.912793568,"remaining_time":2.279351829},
{"learn":[1.520925032],"iteration":561,"passed_time":2.915588457,"remaining_time":2.27229136},
{"learn":[1.517889425],"iteration":562,"passed_time":2.918591757,"remaining_time":2.265407811},
{"learn":[1.516389453],"iteration":563,"passed_time":2.921618405,"remaining_time":2.258556072},
{"learn":[1.515940458],"iteration":564,"passed_time":2.925346236,"remaining_time":2.252257722},
{"learn":[1.515156956],"iteration":565,"passed_time":2.927936105,"remaining_time":2.245095882},
{"learn":[1.514393332],"iteration":566,"passed_time":2.930843176,"remaining_time":2.238192408},
{"learn":[1.513157265],"iteration":567,"passed_time":2.933862983,"remaining_time":2.231388747},
{"learn":[1.512614409],"iteration":568,"passed_time":2.937481859,"remaining_time":2.225052164},
{"learn":[1.511487724],"iteration":569,"passed_time":2.940417496,"remaining_time":2.21820969},
{"learn":[1.510386915],"iteration":570,"passed_time":2.942907259,"remaining_time":2.211045909},
{"learn":[1.509344116],"iteration":571,"passed_time":2.945646363,"remaining_time":2.204085041},
{"learn":[1.50854156],"iteration":572,"passed_time":2.948334197,"remaining_time":2.197100702},
{"learn":[1.508086698],"iteration":573,"passed_time":2.950945625,"remaining_time":2.190074627},
{"learn":[1.507277058],"iteration":574,"passed_time":2.95422754,"remaining_time":2.183559486},
{"learn":[1.50646592],"iteration":575,"passed_time":2.956766791,"remaining_time":2.176508888},
{"learn":[1.504758761],"iteration":576,"passed_time":2.959306491,"remaining_time":2.169474256},
{"learn":[1.503262176],"iteration":577,"passed_time":2.961794804,"remaining_time":2.16241766},
{"learn":[1.500428221],"iteration":578,"passed_time":2.964143725,"remaining_time":2.155275489},
{"learn":[1.4993351],"iteration":579,"passed_time":2.967650692,"remaining_time":2.148988432},
{"learn":[1.498696517],"iteration":580,"passed_time":2.970833868,"remaining_time":2.142477437},
{"learn":[1.497385314],"iteration":581,"passed_time":2.973707856,"remaining_time":2.135755814},
{"learn":[1.495755415],"iteration":582,"passed_time":2.976800277,"remaining_time":2.129203629},
{"learn":[1.495111746],"iteration":583,"passed_time":2.979776844,"remaining_time":2.122580766},
{"learn":[1.494832662],"iteration":584,"passed_time":2.984259303,"remaining_time":2.11703865},
{"learn":[1.493509533],"iteration":585,"passed_time":2.987376775,"remaining_time":2.11053581},
{"learn":[1.492279748],"iteration":586,"passed_time":2.990282984,"remaining_time":2.103895864},
{"learn":[1.490237711],"iteration":587,"passed_time":2.993598357,"remaining_time":2.097555311},
{"learn":[1.490042236],"iteration":588,"passed_time":2.996862228,"remaining_time":2.091189093},
{"learn":[1.489161333],"iteration":589,"passed_time":3.000239968,"remaining_time":2.08491252},
{"learn":[1.488137473],"iteration":590,"passed_time":3.003441612,"remaining_time":2.078523891},
{"learn":[1.48744928],"iteration":591,"passed_time":3.0064728,"remaining_time":2.072028552},
{"learn":[1.486407363],"iteration":592,"passed_time":3.009670449,"remaining_time":2.065659144},
{"learn":[1.485430385],"iteration":593,"passed_time":3.014211232,"remaining_time":2.060218451},
{"learn":[1.484599295],"iteration":594,"passed_time":3.017334811,"remaining_time":2.053816132},
{"learn":[1.484226255],"iteration":595,"passed_time":3.020278619,"remaining_time":2.047302957},
{"learn":[1.483315743],"iteration":596,"passed_time":3.023466195,"remaining_time":2.040966292},
{"learn":[1.483174168],"iteration":597,"passed_time":3.02639192,"remaining_time":2.034464134},
{"learn":[1.482061726],"iteration":598,"passed_time":3.030153043,"remaining_time":2.028533172},
{"learn":[1.481930329],"iteration":599,"passed_time":3.033039295,"remaining_time":2.022026196},
{"learn":[1.480209578],"iteration":600,"passed_time":3.036236773,"remaining_time":2.015737891},
{"learn":[1.47947139],"iteration":601,"passed_time":3.039624213,"remaining_time":2.009585443},
{"learn":[1.479076316],"iteration":602,"passed_time":3.04355773,"remaining_time":2.003801689},
{"learn":[1.478031131],"iteration":603,"passed_time":3.046844832,"remaining_time":1.997600254},
{"learn":[1.477085828],"iteration":604,"passed_time":3.049702084,"remaining_time":1.991127807},
{"learn":[1.476486582],"iteration":605,"passed_time":3.052996375,"remaining_time":1.984951439},
{"learn":[1.475467464],"iteration":606,"passed_time":3.05620427,"remaining_time":1.97872863},
{"learn":[1.475156635],"iteration":607,"passed_time":3.060731673,"remaining_time":1.973366474},
{"learn":[1.474095826],"iteration":608,"passed_time":3.063799751,"remaining_time":1.967070119},
{"learn":[1.472640588],"iteration":609,"passed_time":3.067048598,"remaining_time":1.960899923},
{"learn":[1.472037166],"iteration":610,"passed_time":3.069983412,"remaining_time":1.954539357},
{"learn":[1.471032889],"iteration":611,"passed_time":3.074312592,"remaining_time":1.949073996},
{"learn":[1.470217755],"iteration":612,"passed_time":3.077611628,"remaining_time":1.942961991},
{"learn":[1.468680542],"iteration":613,"passed_time":3.080732027,"remaining_time":1.936746845},
{"learn":[1.467249306],"iteration":614,"passed_time":3.084172997,"remaining_time":1.930742445},
{"learn":[1.466772683],"iteration":615,"passed_time":3.088848845,"remaining_time":1.925516163},
{"learn":[1.466217104],"iteration":616,"passed_time":3.091912904,"remaining_time":1.919291154},
{"learn":[1.465975442],"iteration":617,"passed_time":3.094941691,"remaining_time":1.913054573},
{"learn":[1.465743534],"iteration":618,"passed_time":3.098107231,"remaining_time":1.906912528},
{"learn":[1.464627695],"iteration":619,"passed_time":3.101371026,"remaining_time":1.900840306},
{"learn":[1.464376084],"iteration":620,"passed_time":3.105682677,"remaining_time":1.895416642},
{"learn":[1.463422066],"iteration":621,"passed_time":3.108996354,"remaining_time":1.889390067},
{"learn":[1.462652761],"iteration":622,"passed_time":3.112133993,"remaining_time":1.883265675},
{"learn":[1.461208285],"iteration":623,"passed_time":3.115504985,"remaining_time":1.877291465},
{"learn":[1.459131161],"iteration":624,"passed_time":3.119827111,"remaining_time":1.871896267},
{"learn":[1.458446477],"iteration":625,"passed_time":3.1230227,"remaining_time":1.865831453},
{"learn":[1.455427311],"iteration":626,"passed_time":3.126153937,"remaining_time":1.859737509},
{"learn":[1.454636721],"iteration":627,"passed_time":3.129263141,"remaining_time":1.85363995},
{"learn":[1.454181315],"iteration":628,"passed_time":3.133716755,"remaining_time":1.848344859},
{"learn":[1.453439203],"iteration":629,"passed_time":3.137129925,"remaining_time":1.842441385},
{"learn":[1.452453899],"iteration":630,"passed_time":3.140343737,"remaining_time":1.836429222},
{"learn":[1.451294459],"iteration":631,"passed_time":3.143460336,"remaining_time":1.830369309},
{"learn":[1.449937942],"iteration":632,"passed_time":3.147372824,"remaining_time":1.824780136},
{"learn":[1.448823015],"iteration":633,"passed_time":3.150739546,"remaining_time":1.818881189},
{"learn":[1.44779327],"iteration":634,"passed_time":3.153872976,"remaining_time":1.81285612},
{"learn":[1.44690212],"iteration":635,"passed_time":3.157044307,"remaining_time":1.806861836},
{"learn":[1.446460942],"iteration":636,"passed_time":3.160494462,"remaining_time":1.801035306},
{"learn":[1.445264962],"iteration":637,"passed_time":3.164761833,"remaining_time":1.795679911},
{"learn":[1.445065816],"iteration":638,"passed_time":3.168252321,"remaining_time":1.789889026},
{"learn":[1.444770819],"iteration":639,"passed_time":3.171327882,"remaining_time":1.783871934},
{"learn":[1.444318251],"iteration":640,"passed_time":3.17453912,"remaining_time":1.777940006},
{"learn":[1.443604811],"iteration":641,"passed_time":3.179645058,"remaining_time":1.773073101},
{"learn":[1.442944926],"iteration":642,"passed_time":3.183021982,"remaining_time":1.767245486},
{"learn":[1.441844047],"iteration":643,"passed_time":3.186322289,"remaining_time":1.761383129},
{"learn":[1.441006274],"iteration":644,"passed_time":3.189419955,"remaining_time":1.755417184},
{"learn":[1.440127017],"iteration":645,"passed_time":3.193701098,"remaining_time":1.750108651},
{"learn":[1.439973928],"iteration":646,"passed_time":3.197311659,"remaining_time":1.744437428},
{"learn":[1.439274887],"iteration":647,"passed_time":3.200507831,"remaining_time":1.738547464},
{"learn":[1.43843262],"iteration":648,"passed_time":3.204181054,"remaining_time":1.732923806},
{"learn":[1.438234574],"iteration":649,"passed_time":3.20831065,"remaining_time":1.727551888},
{"learn":[1.437576602],"iteration":650,"passed_time":3.212192081,"remaining_time":1.722050747},
{"learn":[1.436738796],"iteration":651,"passed_time":3.21539179,"remaining_time":1.71619071},
{"learn":[1.435932244],"iteration":652,"passed_time":3.218752555,"remaining_time":1.710424405},
{"learn":[1.434285137],"iteration":653,"passed_time":3.222313232,"remaining_time":1.70477122},
{"learn":[1.43393313],"iteration":654,"passed_time":3.226140857,"remaining_time":1.699265032},
{"learn":[1.433338393],"iteration":655,"passed_time":3.229587586,"remaining_time":1.693564222},
{"learn":[1.433064469],"iteration":656,"passed_time":3.232843624,"remaining_time":1.68777072},
{"learn":[1.431847711],"iteration":657,"passed_time":3.236206758,"remaining_time":1.682040595},
{"learn":[1.431300186],"iteration":658,"passed_time":3.240612774,"remaining_time":1.676857293},
{"learn":[1.430449431],"iteration":659,"passed_time":3.243980658,"remaining_time":1.671141551},
{"learn":[1.429955769],"iteration":660,"passed_time":3.247151131,"remaining_time":1.665331669},
{"learn":[1.428359059],"iteration":661,"passed_time":3.250804714,"remaining_time":1.659776425},
{"learn":[1.427889384],"iteration":662,"passed_time":3.255323212,"remaining_time":1.65466655},
{"learn":[1.425521805],"iteration":663,"passed_time":3.258566583,"remaining_time":1.64891321},
{"learn":[1.425363049],"iteration":664,"passed_time":3.261764278,"remaining_time":1.643144411},
{"learn":[1.425140538],"iteration":665,"passed_time":3.265045235,"remaining_time":1.637425088},
{"learn":[1.424713689],"iteration":666,"passed_time":3.269678806,"remaining_time":1.63238837},
{"learn":[1.424486161],"iteration":667,"passed_time":3.273310175,"remaining_time":1.626854758},
{"learn":[1.421731847],"iteration":668,"passed_time":3.276954779,"remaining_time":1.621333381},
{"learn":[1.420795695],"iteration":669,"passed_time":3.28031446,"remaining_time":1.615677272},
{"learn":[1.420321149],"iteration":670,"passed_time":3.285058199,"remaining_time":1.610706628},
{"learn":[1.420107772],"iteration":671,"passed_time":3.288646622,"remaining_time":1.605172756},
{"learn":[1.419634336],"iteration":672,"passed_time":3.292134376,"remaining_time":1.599595752},
{"learn":[1.419065024],"iteration":673,"passed_time":3.295771359,"remaining_time":1.594097126},
{"learn":[1.418789514],"iteration":674,"passed_time":3.30088476,"remaining_time":1.589314884},
{"learn":[1.418165195],"iteration":675,"passed_time":3.304478079,"remaining_time":1.583803103},
{"learn":[1.41673739],"iteration":676,"passed_time":3.308097827,"remaining_time":1.578309598},
{"learn":[1.416017391],"iteration":677,"passed_time":3.311643067,"remaining_time":1.572786235},
{"learn":[1.414505035],"iteration":678,"passed_time":3.316275047,"remaining_time":1.56778246},
{"learn":[1.413818284],"iteration":679,"passed_time":3.319820967,"remaining_time":1.56226869},
{"learn":[1.412979526],"iteration":680,"passed_time":3.323417994,"remaining_time":1.55678464},
{"learn":[1.412655888],"iteration":681,"passed_time":3.327178689,"remaining_time":1.551382439},
{"learn":[1.41049338],"iteration":682,"passed_time":3.331705501,"remaining_time":1.54634062},
{"learn":[1.409578888],"iteration":683,"passed_time":3.335451902,"remaining_time":1.540939768},
{"learn":[1.4093913],"iteration":684,"passed_time":3.338738911,"remaining_time":1.535332492},
{"learn":[1.408199319],"iteration":685,"passed_time":3.342677197,"remaining_time":1.530030087},
{"learn":[1.407918168],"iteration":686,"passed_time":3.347011963,"remaining_time":1.524912292},
{"learn":[1.407029536],"iteration":687,"passed_time":3.35107311,"remaining_time":1.519672689},
{"learn":[1.406854987],"iteration":688,"passed_time":3.354492087,"remaining_time":1.514146646},
{"learn":[1.404927344],"iteration":689,"passed_time":3.358398461,"remaining_time":1.508845686},
{"learn":[1.404314206],"iteration":690,"passed_time":3.36281159,"remaining_time":1.503775371},
{"learn":[1.403761404],"iteration":691,"passed_time":3.366268998,"remaining_time":1.498281577},
{"learn":[1.403009728],"iteration":692,"passed_time":3.369905779,"remaining_time":1.492873123},
{"learn":[1.402236511],"iteration":693,"passed_time":3.373957428,"remaining_time":1.487652699},
{"learn":[1.401377815],"iteration":694,"passed_time":3.377937909,"remaining_time":1.482404406},
{"learn":[1.401120177],"iteration":695,"passed_time":3.381738491,"remaining_time":1.47708118},
{"learn":[1.400884736],"iteration":696,"passed_time":3.385102532,"remaining_time":1.47157255},
{"learn":[1.400632296],"iteration":697,"passed_time":3.389005354,"remaining_time":1.466303176},
{"learn":[1.400092662],"iteration":698,"passed_time":3.392614204,"remaining_time":1.460911123},
{"learn":[1.399847445],"iteration":699,"passed_time":3.396513306,"remaining_time":1.45564856},
{"learn":[1.398437864],"iteration":700,"passed_time":3.400006462,"remaining_time":1.450216736},
{"learn":[1.39662571],"iteration":701,"passed_time":3.40409106,"remaining_time":1.445041504},
{"learn":[1.396130894],"iteration":702,"passed_time":3.407885521,"remaining_time":1.439746799},
{"learn":[1.395302001],"iteration":703,"passed_time":3.411165524,"remaining_time":1.43424005},
{"learn":[1.394438417],"iteration":704,"passed_time":3.41503532,"remaining_time":1.42898641},
{"learn":[1.39279542],"iteration":705,"passed_time":3.418777463,"remaining_time":1.423683533},
{"learn":[1.392668895],"iteration":706,"passed_time":3.42314279,"remaining_time":1.418643334},
{"learn":[1.392035474],"iteration":707,"passed_time":3.426615,"remaining_time":1.413236695},
{"learn":[1.391257039],"iteration":708,"passed_time":3.430182607,"remaining_time":1.407874666},
{"learn":[1.391107207],"iteration":709,"passed_time":3.434002252,"remaining_time":1.402620638},
{"learn":[1.389677885],"iteration":710,"passed_time":3.438145169,"remaining_time":1.397502045},
{"learn":[1.389404289],"iteration":711,"passed_time":3.441510211,"remaining_time":1.392071546},
{"learn":[1.388656651],"iteration":712,"passed_time":3.445273167,"remaining_time":1.386807011},
{"learn":[1.387976617],"iteration":713,"passed_time":3.449785111,"remaining_time":1.381846697},
{"learn":[1.386929484],"iteration":714,"passed_time":3.453314749,"remaining_time":1.376496089},
{"learn":[1.38658777],"iteration":715,"passed_time":3.457017419,"remaining_time":1.3712192},
{"learn":[1.385644668],"iteration":716,"passed_time":3.460359081,"remaining_time":1.365804212},
{"learn":[1.385430956],"iteration":717,"passed_time":3.464898664,"remaining_time":1.360865492},
{"learn":[1.384556367],"iteration":718,"passed_time":3.468371892,"remaining_time":1.355511129},
{"learn":[1.382764022],"iteration":719,"passed_time":3.472005052,"remaining_time":1.350224187},
{"learn":[1.382253226],"iteration":720,"passed_time":3.475500919,"remaining_time":1.344888705},
{"learn":[1.381051448],"iteration":721,"passed_time":3.480227319,"remaining_time":1.340032126},
{"learn":[1.379803018],"iteration":722,"passed_time":3.483776611,"remaining_time":1.334724926},
{"learn":[1.379196478],"iteration":723,"passed_time":3.487203874,"remaining_time":1.329376062},
{"learn":[1.378668754],"iteration":724,"passed_time":3.491514531,"remaining_time":1.324367581},
{"learn":[1.37786751],"iteration":725,"passed_time":3.494922479,"remaining_time":1.319020329},
{"learn":[1.376651684],"iteration":726,"passed_time":3.49871022,"remaining_time":1.313821032},
{"learn":[1.376451664],"iteration":727,"passed_time":3.502290127,"remaining_time":1.308547959},
{"learn":[1.375609487],"iteration":728,"passed_time":3.506685263,"remaining_time":1.303582587},
{"learn":[1.375475664],"iteration":729,"passed_time":3.510114033,"remaining_time":1.298261355},
{"learn":[1.374817995],"iteration":730,"passed_time":3.513969101,"remaining_time":1.293102173},
{"learn":[1.373989047],"iteration":731,"passed_time":3.517409945,"remaining_time":1.287794898},
{"learn":[1.373072687],"iteration":732,"passed_time":3.522000515,"remaining_time":1.282911511},
{"learn":[1.37281057],"iteration":733,"passed_time":3.525255482,"remaining_time":1.277544902},
{"learn":[1.372483096],"iteration":734,"passed_time":3.528760736,"remaining_time":1.272274279},
{"learn":[1.37197583],"iteration":735,"passed_time":3.532216921,"remaining_time":1.266990852},
{"learn":[1.371021665],"iteration":736,"passed_time":3.537657443,"remaining_time":1.262420499},
{"learn":[1.37076406],"iteration":737,"passed_time":3.541120054,"remaining_time":1.257145602},
{"learn":[1.368411964],"iteration":738,"passed_time":3.54475652,"remaining_time":1.251937012},
{"learn":[1.367048446],"iteration":739,"passed_time":3.548177828,"remaining_time":1.246657075},
{"learn":[1.366543383],"iteration":740,"passed_time":3.552984589,"remaining_time":1.241866408},
{"learn":[1.36575128],"iteration":741,"passed_time":3.557225763,"remaining_time":1.236879039},
{"learn":[1.365566578],"iteration":742,"passed_time":3.561071312,"remaining_time":1.231756833},
{"learn":[1.36468087],"iteration":743,"passed_time":3.565004328,"remaining_time":1.226668156},
{"learn":[1.364008524],"iteration":744,"passed_time":3.569996701,"remaining_time":1.22194518},
{"learn":[1.363300071],"iteration":745,"passed_time":3.573560205,"remaining_time":1.216734976},
{"learn":[1.362207872],"iteration":746,"passed_time":3.577126309,"remaining_time":1.211530062},
{"learn":[1.360777733],"iteration":747,"passed_time":3.581341839,"remaining_time":1.20654832},
{"learn":[1.358929638],"iteration":748,"passed_time":3.585194813,"remaining_time":1.201447127},
{"learn":[1.358809506],"iteration":749,"passed_time":3.588339942,"remaining_time":1.196113314},
{"learn":[1.358446039],"iteration":750,"passed_time":3.591783421,"remaining_time":1.19088425},
{"learn":[1.357162228],"iteration":751,"passed_time":3.595992053,"remaining_time":1.185912273},
{"learn":[1.356355102],"iteration":752,"passed_time":3.599752888,"remaining_time":1.180795436},
{"learn":[1.35562505],"iteration":753,"passed_time":3.603165663,"remaining_time":1.175568638},
{"learn":[1.35486711],"iteration":754,"passed_time":3.606607838,"remaining_time":1.170356186},
{"learn":[1.354179188],"iteration":755,"passed_time":3.610037559,"remaining_time":1.165144397},
{"learn":[1.353444419],"iteration":756,"passed_time":3.614095369,"remaining_time":1.160138936},
{"learn":[1.351243061],"iteration":757,"passed_time":3.61770456,"remaining_time":1.154992749},
{"learn":[1.351094409],"iteration":758,"passed_time":3.62125805,"remaining_time":1.149832925},
{"learn":[1.350528525],"iteration":759,"passed_time":3.625960326,"remaining_time":1.145040103},
{"learn":[1.350401672],"iteration":760,"passed_time":3.629834742,"remaining_time":1.139987521},
{"learn":[1.349796186],"iteration":761,"passed_time":3.633202998,"remaining_time":1.134779939},
{"learn":[1.349087995],"iteration":762,"passed_time":3.636740788,"remaining_time":1.129629838},
{"learn":[1.348501081],"iteration":763,"passed_time":3.640276008,"remaining_time":1.124483165},
{"learn":[1.347865875],"iteration":764,"passed_time":3.644651158,"remaining_time":1.119598722},
{"learn":[1.345769186],"iteration":765,"passed_time":3.647993428,"remaining_time":1.114400081},
{"learn":[1.345477404],"iteration":766,"passed_time":3.651483291,"remaining_time":1.109251117},
{"learn":[1.344936002],"iteration":767,"passed_time":3.655270472,"remaining_time":1.104196288},
{"learn":[1.343973968],"iteration":768,"passed_time":3.662847157,"remaining_time":1.100283086},
{"learn":[1.342931794],"iteration":769,"passed_time":3.666295299,"remaining_time":1.095127167},
{"learn":[1.342439583],"iteration":770,"passed_time":3.669607633,"remaining_time":1.089935341},
{"learn":[1.341469937],"iteration":771,"passed_time":3.673774511,"remaining_time":1.085000762},
{"learn":[1.340925917],"iteration":772,"passed_time":3.677152635,"remaining_time":1.079836544},
{"learn":[1.340353203],"iteration":773,"passed_time":3.680479075,"remaining_time":1.074661849},
{"learn":[1.339754307],"iteration":774,"passed_time":3.684080646,"remaining_time":1.069571801},
{"learn":[1.338489187],"iteration":775,"passed_time":3.688562958,"remaining_time":1.064739823},
{"learn":[1.337963468],"iteration":776,"passed_time":3.692060311,"remaining_time":1.059626061},
{"learn":[1.336674385],"iteration":777,"passed_time":3.695467193,"remaining_time":1.054490639},
{"learn":[1.336120188],"iteration":778,"passed_time":3.699037594,"remaining_time":1.049406044},
{"learn":[1.335300366],"iteration":779,"passed_time":3.703527937,"remaining_time":1.044584803},
{"learn":[1.334774759],"iteration":780,"passed_time":3.707138811,"remaining_time":1.039517797},
{"learn":[1.334076159],"iteration":781,"passed_time":3.710523021,"remaining_time":1.034391328},
{"learn":[1.333215],"iteration":782,"passed_time":3.714399649,"remaining_time":1.029405777},
{"learn":[1.332659575],"iteration":783,"passed_time":3.719538772,"remaining_time":1.024770886},
{"learn":[1.33212003],"iteration":784,"passed_time":3.723314341,"remaining_time":1.019761253},
{"learn":[1.330864186],"iteration":785,"passed_time":3.726943162,"remaining_time":1.014714805},
{"learn":[1.330265093],"iteration":786,"passed_time":3.731103991,"remaining_time":1.009815947},
{"learn":[1.32995249],"iteration":787,"passed_time":3.73551405,"remaining_time":1.004986013},
{"learn":[1.329456097],"iteration":788,"passed_time":3.739321499,"remaining_time":0.9999959903},
{"learn":[1.328615062],"iteration":789,"passed_time":3.742891586,"remaining_time":0.9949458645},
{"learn":[1.327830657],"iteration":790,"passed_time":3.748066592,"remaining_time":0.9903235371},
{"learn":[1.327262622],"iteration":791,"passed_time":3.75167261,"remaining_time":0.9852877561},
{"learn":[1.326099009],"iteration":792,"passed_time":3.755439375,"remaining_time":0.9802975417},
{"learn":[1.325537949],"iteration":793,"passed_time":3.759108352,"remaining_time":0.9752850384},
{"learn":[1.324572141],"iteration":794,"passed_time":3.764660029,"remaining_time":0.9707613911},
{"learn":[1.324023843],"iteration":795,"passed_time":3.768285119,"remaining_time":0.9657414124},
{"learn":[1.322670803],"iteration":796,"passed_time":3.772170291,"remaining_time":0.9607911783},
{"learn":[1.32213671],"iteration":797,"passed_time":3.77762188,"remaining_time":0.9562401249},
{"learn":[1.321483672],"iteration":798,"passed_time":3.781797694,"remaining_time":0.9513658781},
{"learn":[1.320841543],"iteration":799,"passed_time":3.785399733,"remaining_time":0.9463499333},
{"learn":[1.320547492],"iteration":800,"passed_time":3.788786932,"remaining_time":0.9412841441},
{"learn":[1.319600682],"iteration":801,"passed_time":3.793391993,"remaining_time":0.9365232103},
{"learn":[1.319002727],"iteration":802,"passed_time":3.79718231,"remaining_time":0.9315627834},
{"learn":[1.318556058],"iteration":803,"passed_time":3.800625471,"remaining_time":0.9265206373},
{"learn":[1.317653961],"iteration":804,"passed_time":3.804354401,"remaining_time":0.9215516873},
{"learn":[1.317176481],"iteration":805,"passed_time":3.80918443,"remaining_time":0.9168508429},
{"learn":[1.316744946],"iteration":806,"passed_time":3.812612567,"remaining_time":0.9118144058},
{"learn":[1.316400684],"iteration":807,"passed_time":3.816085123,"remaining_time":0.9067925044},
{"learn":[1.315862603],"iteration":808,"passed_time":3.819631685,"remaining_time":0.901791906},
{"learn":[1.314818004],"iteration":809,"passed_time":3.824210899,"remaining_time":0.8970371245},
{"learn":[1.314271791],"iteration":810,"passed_time":3.827701131,"remaining_time":0.8920289934},
{"learn":[1.312577719],"iteration":811,"passed_time":3.831044629,"remaining_time":0.8869906283},
{"learn":[1.312063797],"iteration":812,"passed_time":3.834669461,"remaining_time":0.882021143},
{"learn":[1.310951675],"iteration":813,"passed_time":3.83945288,"remaining_time":0.8773196998},
{"learn":[1.310540722],"iteration":814,"passed_time":3.842968882,"remaining_time":0.8723303598},
{"learn":[1.310390911],"iteration":815,"passed_time":3.8464159,"remaining_time":0.8673290755},
{"learn":[1.309528241],"iteration":816,"passed_time":3.850678205,"remaining_time":0.8625142125},
{"learn":[1.309037853],"iteration":817,"passed_time":3.85568053,"remaining_time":0.8578653502},
{"learn":[1.307926715],"iteration":818,"passed_time":3.859461884,"remaining_time":0.8529457887},
{"learn":[1.306588476],"iteration":819,"passed_time":3.863005542,"remaining_time":0.8479768263},
{"learn":[1.306481283],"iteration":820,"passed_time":3.866520722,"remaining_time":0.8430051269},
{"learn":[1.305566478],"iteration":821,"passed_time":3.871161588,"remaining_time":0.8382807331},
{"learn":[1.305044741],"iteration":822,"passed_time":3.874971504,"remaining_time":0.8333778325},
{"learn":[1.304848986],"iteration":823,"passed_time":3.878534974,"remaining_time":0.8284249458},
{"learn":[1.30280578],"iteration":824,"passed_time":3.883074644,"remaining_time":0.8236825002},
{"learn":[1.302589651],"iteration":825,"passed_time":3.887216776,"remaining_time":0.8188568027},
{"learn":[1.301334458],"iteration":826,"passed_time":3.89137544,"remaining_time":0.8140362165},
{"learn":[1.300308411],"iteration":827,"passed_time":3.895372582,"remaining_time":0.8091836765},
{"learn":[1.299445325],"iteration":828,"passed_time":3.901087571,"remaining_time":0.8046875449},
{"learn":[1.299129213],"iteration":829,"passed_time":3.904544475,"remaining_time":0.7997259768},
{"learn":[1.298322392],"iteration":830,"passed_time":3.908143762,"remaining_time":0.7947969865},
{"learn":[1.296602611],"iteration":831,"passed_time":3.911991513,"remaining_time":0.7899213631},
{"learn":[1.296423831],"iteration":832,"passed_time":3.916642376,"remaining_time":0.7852092158},
{"learn":[1.295781775],"iteration":833,"passed_time":3.920588554,"remaining_time":0.7803569545},
{"learn":[1.295255525],"iteration":834,"passed_time":3.923940188,"remaining_time":0.7753893785},
{"learn":[1.294834271],"iteration":835,"passed_time":3.928926952,"remaining_time":0.7707464355},
{"learn":[1.293773682],"iteration":836,"passed_time":3.93273277,"remaining_time":0.76587269},
{"learn":[1.293612895],"iteration":837,"passed_time":3.936234688,"remaining_time":0.760942744},
{"learn":[1.292854],"iteration":838,"passed_time":3.939767584,"remaining_time":0.7560221466},
{"learn":[1.292405173],"iteration":839,"passed_time":3.94487316,"remaining_time":0.7514044115},
{"learn":[1.291158315],"iteration":840,"passed_time":3.948554016,"remaining_time":0.7465161575},
{"learn":[1.290566035],"iteration":841,"passed_time":3.952000731,"remaining_time":0.7415868356},
{"learn":[1.289855102],"iteration":842,"passed_time":3.956508326,"remaining_time":0.7368586088},
{"learn":[1.289695946],"iteration":843,"passed_time":3.961382385,"remaining_time":0.7321986399},
{"learn":[1.288826179],"iteration":844,"passed_time":3.964885317,"remaining_time":0.7272866557},
{"learn":[1.288373192],"iteration":845,"passed_time":3.968281141,"remaining_time":0.7223585056},
{"learn":[1.288004936],"iteration":846,"passed_time":3.972173565,"remaining_time":0.7175236782},
{"learn":[1.287876299],"iteration":847,"passed_time":3.977263801,"remaining_time":0.7129057757},
{"learn":[1.287049165],"iteration":848,"passed_time":3.980819599,"remaining_time":0.7080138509},
{"learn":[1.286949388],"iteration":849,"passed_time":3.984206143,"remaining_time":0.7030952017},
{"learn":[1.286133772],"iteration":850,"passed_time":3.987803708,"remaining_time":0.6982171005},
{"learn":[1.285537248],"iteration":851,"passed_time":3.992523226,"remaining_time":0.6935368985},
{"learn":[1.284608735],"iteration":852,"passed_time":3.996449221,"remaining_time":0.688719854},
{"learn":[1.283753191],"iteration":853,"passed_time":3.999954926,"remaining_time":0.6838330436},
{"learn":[1.283156221],"iteration":854,"passed_time":4.004735618,"remaining_time":0.6791656897},
{"learn":[1.28304497],"iteration":855,"passed_time":4.008337768,"remaining_time":0.6742998114},
{"learn":[1.282297008],"iteration":856,"passed_time":4.012045757,"remaining_time":0.6694545429},
{"learn":[1.28175672],"iteration":857,"passed_time":4.015368964,"remaining_time":0.6645482434},
{"learn":[1.280857771],"iteration":858,"passed_time":4.021718521,"remaining_time":0.6601423882},
{"learn":[1.2807053],"iteration":859,"passed_time":4.025479882,"remaining_time":0.6553106785},
{"learn":[1.280341084],"iteration":860,"passed_time":4.028926827,"remaining_time":0.6504306957},
{"learn":[1.278747279],"iteration":861,"passed_time":4.032496021,"remaining_time":0.6455736089},
{"learn":[1.27845785],"iteration":862,"passed_time":4.037399008,"remaining_time":0.6409312447},
{"learn":[1.278360594],"iteration":863,"passed_time":4.040712382,"remaining_time":0.6360380601},
{"learn":[1.277564908],"iteration":864,"passed_time":4.044646988,"remaining_time":0.6312454837},
{"learn":[1.276687719],"iteration":865,"passed_time":4.048850254,"remaining_time":0.6264964596},
{"learn":[1.276443194],"iteration":866,"passed_time":4.052600062,"remaining_time":0.621679133},
{"learn":[1.275909989],"iteration":867,"passed_time":4.055963628,"remaining_time":0.6168055286},
{"learn":[1.275127813],"iteration":868,"passed_time":4.059887984,"remaining_time":0.6120199377},
{"learn":[1.274666248],"iteration":869,"passed_time":4.06375209,"remaining_time":0.6072273238},
{"learn":[1.272773255],"iteration":870,"passed_time":4.068129604,"remaining_time":0.6025128806},
{"learn":[1.272678489],"iteration":871,"passed_time":4.071318172,"remaining_time":0.5976246858},
{"learn":[1.272501885],"iteration":872,"passed_time":4.075069877,"remaining_time":0.5928223074},
{"learn":[1.270929937],"iteration":873,"passed_time":4.079175339,"remaining_time":0.5880733326},
{"learn":[1.270899415],"iteration":874,"passed_time":4.08282132,"remaining_time":0.5832601886},
{"learn":[1.270849345],"iteration":875,"passed_time":4.086053938,"remaining_time":0.5783911967},
{"learn":[1.269986969],"iteration":876,"passed_time":4.08945745,"remaining_time":0.5735499046},
{"learn":[1.269079795],"iteration":877,"passed_time":4.094129399,"remaining_time":0.5688881397},
{"learn":[1.268901647],"iteration":878,"passed_time":4.098160847,"remaining_time":0.5641381826},
{"learn":[1.268341707],"iteration":879,"passed_time":4.101992443,"remaining_time":0.5593626059},
{"learn":[1.267884279],"iteration":880,"passed_time":4.105361881,"remaining_time":0.5545267467},
{"learn":[1.266946451],"iteration":881,"passed_time":4.110121081,"remaining_time":0.5498801447},
{"learn":[1.266830412],"iteration":882,"passed_time":4.113784216,"remaining_time":0.5450880557},
{"learn":[1.266194123],"iteration":883,"passed_time":4.117066619,"remaining_time":0.5402485609},
{"learn":[1.266109107],"iteration":884,"passed_time":4.120706167,"remaining_time":0.5354589935},
{"learn":[1.26559974],"iteration":885,"passed_time":4.126709469,"remaining_time":0.5309761619},
{"learn":[1.264980147],"iteration":886,"passed_time":4.130716254,"remaining_time":0.5262355543},
{"learn":[1.264717926],"iteration":887,"passed_time":4.134082034,"remaining_time":0.521415752},
{"learn":[1.264133975],"iteration":888,"passed_time":4.140194456,"remaining_time":0.516942165},
{"learn":[1.262911185],"iteration":889,"passed_time":4.14402025,"remaining_time":0.5121822781},
{"learn":[1.262230542],"iteration":890,"passed_time":4.147737955,"remaining_time":0.507411265},
{"learn":[1.261457498],"iteration":891,"passed_time":4.210528546,"remaining_time":0.5097949361},
{"learn":[1.260918162],"iteration":892,"passed_time":4.213421664,"remaining_time":0.5048556753},
{"learn":[1.260615541],"iteration":893,"passed_time":4.216857114,"remaining_time":0.4999852954},
{"learn":[1.260176791],"iteration":894,"passed_time":4.22496084,"remaining_time":0.4956657969},
{"learn":[1.260053083],"iteration":895,"passed_time":4.228630226,"remaining_time":0.4908231513},
{"learn":[1.259004241],"iteration":896,"passed_time":4.232175768,"remaining_time":0.4859689009},
{"learn":[1.258543771],"iteration":897,"passed_time":4.23459305,"remaining_time":0.480989411},
{"learn":[1.25807185],"iteration":898,"passed_time":4.23693185,"remaining_time":0.4760068041},
{"learn":[1.257583078],"iteration":899,"passed_time":4.239373517,"remaining_time":0.4710415019},
{"learn":[1.256485292],"iteration":900,"passed_time":4.241955512,"remaining_time":0.4660972205},
{"learn":[1.256363988],"iteration":901,"passed_time":4.245680067,"remaining_time":0.4612823133},
{"learn":[1.255701704],"iteration":902,"passed_time":4.248310283,"remaining_time":0.4563522674},
{"learn":[1.254696283],"iteration":903,"passed_time":4.262813159,"remaining_time":0.4526881231},
{"learn":[1.253510342],"iteration":904,"passed_time":4.265430914,"remaining_time":0.4477524164},
{"learn":[1.253137875],"iteration":905,"passed_time":4.267961108,"remaining_time":0.4428127419},
{"learn":[1.252591627],"iteration":906,"passed_time":4.270501275,"remaining_time":0.437879403},
{"learn":[1.251745379],"iteration":907,"passed_time":4.273057701,"remaining_time":0.4329529829},
{"learn":[1.251217401],"iteration":908,"passed_time":4.276450709,"remaining_time":0.4281155275},
{"learn":[1.250755575],"iteration":909,"passed_time":4.27925072,"remaining_time":0.4232225987},
{"learn":[1.25045325],"iteration":910,"passed_time":4.282226997,"remaining_time":0.4183514849},
{"learn":[1.250001526],"iteration":911,"passed_time":4.285128982,"remaining_time":0.4134773579},
{"learn":[1.249240291],"iteration":912,"passed_time":4.287784325,"remaining_time":0.4085840485},
{"learn":[1.247394052],"iteration":913,"passed_time":4.291452,"remaining_time":0.4037908884},
{"learn":[1.246517462],"iteration":914,"passed_time":4.294247172,"remaining_time":0.3989191362},
{"learn":[1.245558452],"iteration":915,"passed_time":4.297152726,"remaining_time":0.3940620404},
{"learn":[1.244582685],"iteration":916,"passed_time":4.300153373,"remaining_time":0.389217808},
{"learn":[1.243847153],"iteration":917,"passed_time":4.302633944,"remaining_time":0.3843311366},
{"learn":[1.242101219],"iteration":918,"passed_time":4.306182416,"remaining_time":0.3795438256},
{"learn":[1.241108649],"iteration":919,"passed_time":4.30901877,"remaining_time":0.3746972843},
{"learn":[1.240027253],"iteration":920,"passed_time":4.311491459,"remaining_time":0.3698239145},
{"learn":[1.239932312],"iteration":921,"passed_time":4.314427922,"remaining_time":0.3649949869},
{"learn":[1.239542649],"iteration":922,"passed_time":4.316950858,"remaining_time":0.360135662},
{"learn":[1.238714131],"iteration":923,"passed_time":4.319689736,"remaining_time":0.3552991558},
{"learn":[1.23806994],"iteration":924,"passed_time":4.323343868,"remaining_time":0.3505413947},
{"learn":[1.236718933],"iteration":925,"passed_time":4.326243823,"remaining_time":0.3457257483},
{"learn":[1.236265391],"iteration":926,"passed_time":4.328662027,"remaining_time":0.3408762977},
{"learn":[1.235400324],"iteration":927,"passed_time":4.331396637,"remaining_time":0.3360566356},
{"learn":[1.235253612],"iteration":928,"passed_time":4.333818288,"remaining_time":0.3312175441},
{"learn":[1.235146959],"iteration":929,"passed_time":4.337943878,"remaining_time":0.3265119048},
{"learn":[1.234268155],"iteration":930,"passed_time":4.340492483,"remaining_time":0.3216906351},
{"learn":[1.233419264],"iteration":931,"passed_time":4.342869752,"remaining_time":0.3168617416},
{"learn":[1.233101377],"iteration":932,"passed_time":4.345236631,"remaining_time":0.3120373572},
{"learn":[1.232658257],"iteration":933,"passed_time":4.347944595,"remaining_time":0.3072423375},
{"learn":[1.231678565],"iteration":934,"passed_time":4.351650582,"remaining_time":0.3025211635},
{"learn":[1.231236483],"iteration":935,"passed_time":4.354336072,"remaining_time":0.297732381},
{"learn":[1.230176646],"iteration":936,"passed_time":4.356845228,"remaining_time":0.292936232},
{"learn":[1.22975847],"iteration":937,"passed_time":4.359444554,"remaining_time":0.2881509193},
{"learn":[1.228989224],"iteration":938,"passed_time":4.361903956,"remaining_time":0.2833611729},
{"learn":[1.228062735],"iteration":939,"passed_time":4.36427418,"remaining_time":0.2785706923},
{"learn":[1.227560644],"iteration":940,"passed_time":4.367832801,"remaining_time":0.2738598675},
{"learn":[1.226671257],"iteration":941,"passed_time":4.370367331,"remaining_time":0.2690884344},
{"learn":[1.226425048],"iteration":942,"passed_time":4.372794906,"remaining_time":0.2643152806},
{"learn":[1.225742439],"iteration":943,"passed_time":4.37516227,"remaining_time":0.2595435245},
{"learn":[1.225657975],"iteration":944,"passed_time":4.377987883,"remaining_time":0.2548035276},
{"learn":[1.2246799],"iteration":945,"passed_time":4.381578818,"remaining_time":0.2501112645},
{"learn":[1.224250017],"iteration":946,"passed_time":4.384835188,"remaining_time":0.2454026029},
{"learn":[1.224207418],"iteration":947,"passed_time":4.387600212,"remaining_time":0.2406700538},
{"learn":[1.223473629],"iteration":948,"passed_time":4.390604042,"remaining_time":0.2359544849},
{"learn":[1.22338032],"iteration":949,"passed_time":4.393469996,"remaining_time":0.231235263},
{"learn":[1.222631307],"iteration":950,"passed_time":4.397809569,"remaining_time":0.2265958663},
{"learn":[1.221644105],"iteration":951,"passed_time":4.400642189,"remaining_time":0.2218811188},
{"learn":[1.221225882],"iteration":952,"passed_time":4.403577911,"remaining_time":0.2171754059},
{"learn":[1.219777275],"iteration":953,"passed_time":4.406701813,"remaining_time":0.2124824774},
{"learn":[1.219370688],"iteration":954,"passed_time":4.409454764,"remaining_time":0.2077753554},
{"learn":[1.2187669],"iteration":955,"passed_time":4.413252817,"remaining_time":0.2031204226},
{"learn":[1.218575344],"iteration":956,"passed_time":4.416164499,"remaining_time":0.198427454},
{"learn":[1.217646442],"iteration":957,"passed_time":4.41889794,"remaining_time":0.1937303898},
{"learn":[1.217005503],"iteration":958,"passed_time":4.422093043,"remaining_time":0.1890571582},
{"learn":[1.215933592],"iteration":959,"passed_time":4.425376843,"remaining_time":0.1843907018},
{"learn":[1.215197387],"iteration":960,"passed_time":4.429385483,"remaining_time":0.1797565389},
{"learn":[1.214813035],"iteration":961,"passed_time":4.432297194,"remaining_time":0.1750803465},
{"learn":[1.214322925],"iteration":962,"passed_time":4.435117339,"remaining_time":0.1704043007},
{"learn":[1.213224859],"iteration":963,"passed_time":4.43825585,"remaining_time":0.1657439944},
{"learn":[1.212427136],"iteration":964,"passed_time":4.442221036,"remaining_time":0.1611168252},
{"learn":[1.212056036],"iteration":965,"passed_time":4.445179553,"remaining_time":0.156455595},
{"learn":[1.211600981],"iteration":966,"passed_time":4.44814447,"remaining_time":0.151798105},
{"learn":[1.210910916],"iteration":967,"passed_time":4.451133914,"remaining_time":0.1471449228},
{"learn":[1.210317998],"iteration":968,"passed_time":4.454077416,"remaining_time":0.1424937048},
{"learn":[1.210167208],"iteration":969,"passed_time":4.45821769,"remaining_time":0.1378830213},
{"learn":[1.209710698],"iteration":970,"passed_time":4.461220209,"remaining_time":0.1332393265},
{"learn":[1.20935596],"iteration":971,"passed_time":4.464124648,"remaining_time":0.1285961833},
{"learn":[1.209315649],"iteration":972,"passed_time":4.466786805,"remaining_time":0.1239498908},
{"learn":[1.208612034],"iteration":973,"passed_time":4.470263113,"remaining_time":0.1193294055},
{"learn":[1.207365667],"iteration":974,"passed_time":4.475052031,"remaining_time":0.1147449239},
{"learn":[1.206626062],"iteration":975,"passed_time":4.478135004,"remaining_time":0.1101180739},
{"learn":[1.205555061],"iteration":976,"passed_time":4.481047493,"remaining_time":0.1054903709},
{"learn":[1.205141368],"iteration":977,"passed_time":4.483756603,"remaining_time":0.1008616005},
{"learn":[1.203414987],"iteration":978,"passed_time":4.487995865,"remaining_time":0.09626957423},
{"learn":[1.203068401],"iteration":979,"passed_time":4.491111464,"remaining_time":0.091655336},
{"learn":[1.20263738],"iteration":980,"passed_time":4.494302667,"remaining_time":0.08704561739},
{"learn":[1.201567806],"iteration":981,"passed_time":4.497486536,"remaining_time":0.08243865341},
{"learn":[1.200460734],"iteration":982,"passed_time":4.500699408,"remaining_time":0.07783508641},
{"learn":[1.200421581],"iteration":983,"passed_time":4.504633694,"remaining_time":0.07324607632},
{"learn":[1.199395429],"iteration":984,"passed_time":4.507838606,"remaining_time":0.06864728841},
{"learn":[1.19923054],"iteration":985,"passed_time":4.510843508,"remaining_time":0.06404848794},
{"learn":[1.199198805],"iteration":986,"passed_time":4.514167301,"remaining_time":0.05945711744},
{"learn":[1.199129148],"iteration":987,"passed_time":4.51738274,"remaining_time":0.05486699684},
{"learn":[1.198843348],"iteration":988,"passed_time":4.520849866,"remaining_time":0.05028245553},
{"learn":[1.197928111],"iteration":989,"passed_time":4.523836059,"remaining_time":0.04569531373},
{"learn":[1.196913832],"iteration":990,"passed_time":4.5267794,"remaining_time":0.04111101372},
{"learn":[1.195680616],"iteration":991,"passed_time":4.530153248,"remaining_time":0.03653349394},
{"learn":[1.195305938],"iteration":992,"passed_time":4.534144197,"remaining_time":0.03196274862},
{"learn":[1.194875491],"iteration":993,"passed_time":4.537444906,"remaining_time":0.02738900345},
{"learn":[1.194838048],"iteration":994,"passed_time":4.540603321,"remaining_time":0.02281710212},
{"learn":[1.193186679],"iteration":995,"passed_time":4.543688811,"remaining_time":0.01824774623},
{"learn":[1.19255384],"iteration":996,"passed_time":4.546806346,"remaining_time":0.01368146343},
{"learn":[1.192041511],"iteration":997,"passed_time":4.550617016,"remaining_time":0.009119472978},
{"learn":[1.191614516],"iteration":998,"passed_time":4.553497124,"remaining_time":0.004558055179},
{"learn":[1.19090958],"iteration":999,"passed_time":4.556970531,"remaining_time":0}
]}